[
  {
    "start": 33.666,
    "end": 34.566,
    "text": "cô chú thân mến",
    "textdich": ""
  },
  {
    "start": 35.133,
    "end": 36.2,
    "text": "có phải dạo gần đây",
    "textdich": ""
  },
  {
    "start": 36.233,
    "end": 37.833,
    "text": "cô chú thường xuyên gặp tình trạng này",
    "textdich": ""
  },
  {
    "start": 38.2,
    "end": 38.833,
    "text": "cứ đêm đến",
    "textdich": ""
  },
  {
    "start": 38.833,
    "end": 41.033,
    "text": "vừa mới chợp mắt một chút lại phải bật dậy đi tiểu",
    "textdich": ""
  },
  {
    "start": 41.533,
    "end": 43.433,
    "text": "có khi một đêm đi đến BA đến 4 lần",
    "textdich": ""
  },
  {
    "start": 43.933,
    "end": 45.933,
    "text": "ngủ chẳng tròn giấc người thì mệt mỏi",
    "textdich": ""
  },
  {
    "start": 46.4,
    "end": 48.8,
    "text": "sáng dậy uể oải đầu óc choáng váng",
    "textdich": ""
  },
  {
    "start": 49.166,
    "end": 50.8,
    "text": "cả ngày chẳng còn sức để làm việc gì",
    "textdich": ""
  },
  {
    "start": 51.433,
    "end": 53.133,
    "text": "rồi có khi đang ngồi cùng con cháu",
    "textdich": ""
  },
  {
    "start": 53.5,
    "end": 55.533,
    "text": "mới uống một chén nước đã cảm thấy buồn tiểu",
    "textdich": ""
  },
  {
    "start": 55.966,
    "end": 57.5,
    "text": "phải vội vàng tìm nhà vệ sinh",
    "textdich": ""
  },
  {
    "start": 58.033,
    "end": 59.766,
    "text": "rất bất tiện và cũng khá xấu hổ",
    "textdich": ""
  },
  {
    "start": 60.766,
    "end": 63.5,
    "text": "thật Ra tất cả những dấu hiệu ấy đều đang báo hiệu",
    "textdich": ""
  },
  {
    "start": 63.566,
    "end": 65.633,
    "text": "rằng thận của cô chú đã và đang yếu đi",
    "textdich": ""
  },
  {
    "start": 66.1,
    "end": 68.333,
    "text": "cơ quan mà từ trước đến nay mình ít để ý tới",
    "textdich": ""
  },
  {
    "start": 68.933,
    "end": 71.333,
    "text": "giờ lại đang dần lên tiếng bằng những cơn tiểu đêm",
    "textdich": ""
  },
  {
    "start": 71.633,
    "end": 75.1,
    "text": "mất ngủ mệt mỏi hay thậm chí là sưng phù chân Tay",
    "textdich": ""
  },
  {
    "start": 75.533,
    "end": 76.566,
    "text": "nếu mình cứ để mặc",
    "textdich": ""
  },
  {
    "start": 76.9,
    "end": 79.7,
    "text": "không quan tâm thì lâu dần có thể dẫn tới suy thận",
    "textdich": ""
  },
  {
    "start": 79.8,
    "end": 81.166,
    "text": "một căn bệnh cực kỳ nguy hiểm",
    "textdich": ""
  },
  {
    "start": 81.7,
    "end": 83.2,
    "text": "ảnh hưởng trực tiếp đến tuổi thọ",
    "textdich": ""
  },
  {
    "start": 83.366,
    "end": 84.233,
    "text": "và chất lượng cuộc sống",
    "textdich": ""
  },
  {
    "start": 84.966,
    "end": 85.933,
    "text": "vâng tôi hiểu",
    "textdich": ""
  },
  {
    "start": 86.233,
    "end": 89.1,
    "text": "nhiều cô chú khi nghe tới chữ suy thận là lo lắng lắm",
    "textdich": ""
  },
  {
    "start": 89.7,
    "end": 91.4,
    "text": "bởi vì AI cũng biết rằng thận yếu",
    "textdich": ""
  },
  {
    "start": 91.5,
    "end": 92.733,
    "text": "không chỉ gây Ra tiểu đêm",
    "textdich": ""
  },
  {
    "start": 93.033,
    "end": 95.766,
    "text": "mất ngủ mà còn khiến toàn bộ cơ thể suy kiệt",
    "textdich": ""
  },
  {
    "start": 96.033,
    "end": 96.833,
    "text": "ăn không ngon",
    "textdich": ""
  },
  {
    "start": 97.133,
    "end": 97.933,
    "text": "ngủ không yên",
    "textdich": ""
  },
  {
    "start": 98.1,
    "end": 100.9,
    "text": "huyết áp tăng 7 thường Tim mạch cũng bị ảnh hưởng",
    "textdich": ""
  },
  {
    "start": 101.633,
    "end": 102.4,
    "text": "thậm chí",
    "textdich": ""
  },
  {
    "start": 102.4,
    "end": 104.4,
    "text": "có những trường hợp còn phải chạy thận nhân tạo",
    "textdich": ""
  },
  {
    "start": 104.766,
    "end": 106.033,
    "text": "một quá trình rất tốn kém",
    "textdich": ""
  },
  {
    "start": 106.533,
    "end": 109.3,
    "text": "vất vả và làm Cho cuộc sống không còn được tự do",
    "textdich": ""
  },
  {
    "start": 109.366,
    "end": 110.166,
    "text": "như trước nữa",
    "textdich": ""
  },
  {
    "start": 110.433,
    "end": 111.8,
    "text": "dạ nhưng cô chú yên tâm",
    "textdich": ""
  },
  {
    "start": 112.166,
    "end": 114.2,
    "text": "hôm nay tôi không chỉ nhắc đến những nguy cơ",
    "textdich": ""
  },
  {
    "start": 114.333,
    "end": 115.2,
    "text": "để cô chú lo lắng",
    "textdich": ""
  },
  {
    "start": 115.833,
    "end": 117.633,
    "text": "mà tôi muốn mang đến một Tia hi vọng",
    "textdich": ""
  },
  {
    "start": 117.833,
    "end": 119.333,
    "text": "một bí quyết dân gian đơn giản",
    "textdich": ""
  },
  {
    "start": 119.733,
    "end": 120.533,
    "text": "rẻ tiền",
    "textdich": ""
  },
  {
    "start": 120.7,
    "end": 123.0,
    "text": "nhưng lại có thể giúp thận của cô chú được nghỉ ngơi",
    "textdich": ""
  },
  {
    "start": 123.4,
    "end": 126.1,
    "text": "phục hồi từ đó giảm hẳn tình trạng tiểu đêm",
    "textdich": ""
  },
  {
    "start": 126.433,
    "end": 128.9,
    "text": "ngủ ngon hơn và ngăn chặn suy thận tiến triển",
    "textdich": ""
  },
  {
    "start": 129.833,
    "end": 131.133,
    "text": "cô chú có đoán Ra không",
    "textdich": ""
  },
  {
    "start": 131.566,
    "end": 132.9,
    "text": "đó chính là bột sắn dây",
    "textdich": ""
  },
  {
    "start": 133.133,
    "end": 135.166,
    "text": "một nguyên liệu mà chắc hẳn cô chú đã từng nghe",
    "textdich": ""
  },
  {
    "start": 135.7,
    "end": 137.9,
    "text": "thậm chí có khi còn đang có sẵn trong bếp nhà mình",
    "textdich": ""
  },
  {
    "start": 138.8,
    "end": 140.133,
    "text": "có thể cô chú đang thắc mắc",
    "textdich": ""
  },
  {
    "start": 140.4,
    "end": 142.433,
    "text": "ủa bột sắn dây thì tôi biết chứ",
    "textdich": ""
  },
  {
    "start": 142.7,
    "end": 144.766,
    "text": "thường hay dùng để pha nước giải nhiệt mùa hè",
    "textdich": ""
  },
  {
    "start": 145.433,
    "end": 147.433,
    "text": "nhưng bột sắn dây thì liên quan gì tới thận",
    "textdich": ""
  },
  {
    "start": 147.7,
    "end": 149.633,
    "text": "tới chuyện tiểu đêm mất ngủ đâu",
    "textdich": ""
  },
  {
    "start": 150.166,
    "end": 151.166,
    "text": "vâng chính vì vậy",
    "textdich": ""
  },
  {
    "start": 151.366,
    "end": 154.1,
    "text": "tôi muốn cô chú kiên nhẫn cùng tôi đi hết video này",
    "textdich": ""
  },
  {
    "start": 154.7,
    "end": 156.5,
    "text": "bởi vì tôi sẽ giải thích thật cặn kẽ",
    "textdich": ""
  },
  {
    "start": 156.8,
    "end": 157.633,
    "text": "vì SAO bột sắn",
    "textdich": ""
  },
  {
    "start": 157.833,
    "end": 159.833,
    "text": "dây lại có tác dụng tốt với người thận yếu",
    "textdich": ""
  },
  {
    "start": 160.366,
    "end": 161.633,
    "text": "tại SAO nếu biết cách dùng đúng",
    "textdich": ""
  },
  {
    "start": 161.766,
    "end": 163.566,
    "text": "thì có thể hỗ trợ chặn đứng suy thận",
    "textdich": ""
  },
  {
    "start": 163.833,
    "end": 164.8,
    "text": "giảm hẳn tiểu đêm",
    "textdich": ""
  },
  {
    "start": 165.166,
    "end": 167.566,
    "text": "giúp ngủ sâu giấc hơn và quan trọng hơn",
    "textdich": ""
  },
  {
    "start": 167.766,
    "end": 170.433,
    "text": "tôi sẽ chỉ Cho cô chú cách pha bột sắn dây đúng chuẩn",
    "textdich": ""
  },
  {
    "start": 170.8,
    "end": 171.6,
    "text": "không phải AI cũng biết",
    "textdich": ""
  },
  {
    "start": 172.033,
    "end": 172.833,
    "text": "và nếu làm Sai",
    "textdich": ""
  },
  {
    "start": 172.833,
    "end": 174.0,
    "text": "thì không những không có tác dụng",
    "textdich": ""
  },
  {
    "start": 174.033,
    "end": 176.033,
    "text": "mà đôi khi còn gây hại ngược lại Cho cơ thể",
    "textdich": ""
  },
  {
    "start": 176.8,
    "end": 177.933,
    "text": "cô ơi cô chú biết không",
    "textdich": ""
  },
  {
    "start": 178.166,
    "end": 179.766,
    "text": "từ xa xưa trong đông y",
    "textdich": ""
  },
  {
    "start": 180.166,
    "end": 182.166,
    "text": "sắn dây hay còn gọi là cát căn",
    "textdich": ""
  },
  {
    "start": 182.533,
    "end": 184.366,
    "text": "đã được ghi nhận là có công dụng thanh nhiệt",
    "textdich": ""
  },
  {
    "start": 184.733,
    "end": 187.9,
    "text": "giải độc sinh Tân dịch giải thử nhiệt giải rượu",
    "textdich": ""
  },
  {
    "start": 188.533,
    "end": 190.833,
    "text": "người xưa vẫn dùng bột sắn dây để chữa cảm nắng",
    "textdich": ""
  },
  {
    "start": 191.2,
    "end": 193.9,
    "text": "khát nước hay những trường hợp nóng trong gây nhức đầu",
    "textdich": ""
  },
  {
    "start": 194.2,
    "end": 196.3,
    "text": "khó chịu điều đó Cho thấy bột sắn",
    "textdich": ""
  },
  {
    "start": 196.433,
    "end": 198.633,
    "text": "dây không đơn thuần chỉ là một loại bột để nấu chè",
    "textdich": ""
  },
  {
    "start": 199.033,
    "end": 202.1,
    "text": "pha nước mà thật sự là một vị thuốc quý trong dân gian",
    "textdich": ""
  },
  {
    "start": 203.133,
    "end": 205.433,
    "text": "ngày nay khoa học hiện đại cũng đã phân tích",
    "textdich": ""
  },
  {
    "start": 205.6,
    "end": 207.133,
    "text": "và tìm thấy trong bột sắn dây",
    "textdich": ""
  },
  {
    "start": 207.233,
    "end": 209.366,
    "text": "có nhiều hoạt chất có lợi như puerarin",
    "textdich": ""
  },
  {
    "start": 209.766,
    "end": 211.933,
    "text": "isoflavon genistein",
    "textdich": ""
  },
  {
    "start": 212.366,
    "end": 214.433,
    "text": "những chất này không chỉ giúp điều hòa hormone",
    "textdich": ""
  },
  {
    "start": 214.8,
    "end": 216.133,
    "text": "giảm áp lực Cho mạch máu",
    "textdich": ""
  },
  {
    "start": 216.6,
    "end": 218.0,
    "text": "mà còn có khả năng bảo vệ thận",
    "textdich": ""
  },
  {
    "start": 218.3,
    "end": 220.233,
    "text": "cải thiện tuần hoàn và hỗ trợ giấc ngủ",
    "textdich": ""
  },
  {
    "start": 220.933,
    "end": 223.366,
    "text": "đây chính là điểm mấu chốt mà ít AI biết đến",
    "textdich": ""
  },
  {
    "start": 223.733,
    "end": 225.633,
    "text": "và tôi sẽ chia sẻ kỹ hơn Cho cô chú",
    "textdich": ""
  },
  {
    "start": 225.733,
    "end": 226.7,
    "text": "ở các phần tiếp Theo",
    "textdich": ""
  },
  {
    "start": 227.633,
    "end": 229.033,
    "text": "nhưng trước khi đi vào Chi tiết",
    "textdich": ""
  },
  {
    "start": 229.333,
    "end": 230.5,
    "text": "tôi muốn nhấn mạnh một điều",
    "textdich": ""
  },
  {
    "start": 230.8,
    "end": 231.6,
    "text": "bột sắn dây",
    "textdich": ""
  },
  {
    "start": 231.766,
    "end": 234.1,
    "text": "chỉ phát huy tác dụng khi cô chú dùng đúng cách",
    "textdich": ""
  },
  {
    "start": 234.633,
    "end": 237.233,
    "text": "bởi vì có nhiều người nghe mách nhau liền uống bột sắn",
    "textdich": ""
  },
  {
    "start": 237.433,
    "end": 240.0,
    "text": "sống nghĩ rằng như vậy mới mát mới hiệu quả",
    "textdich": ""
  },
  {
    "start": 240.733,
    "end": 243.033,
    "text": "nhưng thật Ra uống Sai cách có thể gây lạnh bụng",
    "textdich": ""
  },
  {
    "start": 243.333,
    "end": 245.1,
    "text": "tiêu chảy rối loạn tiêu hóa",
    "textdich": ""
  },
  {
    "start": 245.5,
    "end": 247.8,
    "text": "làm cơ thể vốn đã yếu càng thêm suy kiệt",
    "textdich": ""
  },
  {
    "start": 248.3,
    "end": 249.6,
    "text": "đặc biệt là với người thận yếu",
    "textdich": ""
  },
  {
    "start": 250.0,
    "end": 252.3,
    "text": "nếu không biết cách dùng thì lợi bất cập hại",
    "textdich": ""
  },
  {
    "start": 253.166,
    "end": 255.6,
    "text": "Cho nên tôi muốn cô chú hãy lắng nghe thật kỹ",
    "textdich": ""
  },
  {
    "start": 256.1,
    "end": 258.766,
    "text": "tôi hứa rằng trong video này tôi sẽ chỉ Ra",
    "textdich": ""
  },
  {
    "start": 259.7,
    "end": 261.9,
    "text": "vì SAO bột sắn dây tốt Cho người thận yếu",
    "textdich": ""
  },
  {
    "start": 262.533,
    "end": 264.833,
    "text": "2 cách pha và uống bột sắn dây đúng chuẩn",
    "textdich": ""
  },
  {
    "start": 264.966,
    "end": 265.766,
    "text": "để hỗ trợ thận",
    "textdich": ""
  },
  {
    "start": 266.033,
    "end": 266.833,
    "text": "giảm tiểu đêm",
    "textdich": ""
  },
  {
    "start": 267.166,
    "end": 267.966,
    "text": "ngủ ngon",
    "textdich": ""
  },
  {
    "start": 268.6,
    "end": 270.566,
    "text": "những lưu ý quan trọng AI nên dùng",
    "textdich": ""
  },
  {
    "start": 271.0,
    "end": 272.833,
    "text": "AI không nên dùng để tránh phản tác dụng",
    "textdich": ""
  },
  {
    "start": 273.7,
    "end": 275.633,
    "text": "tôi tin rằng sau khi cô chú nghe xong",
    "textdich": ""
  },
  {
    "start": 276.0,
    "end": 277.133,
    "text": "sẽ không còn nhìn bột sắn",
    "textdich": ""
  },
  {
    "start": 277.233,
    "end": 278.566,
    "text": "dây như một loại bột giải khát",
    "textdich": ""
  },
  {
    "start": 278.766,
    "end": 279.566,
    "text": "bình thường nữa",
    "textdich": ""
  },
  {
    "start": 279.733,
    "end": 281.966,
    "text": "mà sẽ xem nó như một người bạn đồng hành của thận",
    "textdich": ""
  },
  {
    "start": 282.3,
    "end": 283.333,
    "text": "giúp cơ thể khỏe mạnh hơn",
    "textdich": ""
  },
  {
    "start": 283.833,
    "end": 285.6,
    "text": "giúp cô chú lấy lại giấc ngủ trọn vẹn",
    "textdich": ""
  },
  {
    "start": 285.9,
    "end": 288.0,
    "text": "không còn cảnh phải chở dậy đi vệ sinh giữa đêm",
    "textdich": ""
  },
  {
    "start": 288.933,
    "end": 291.6,
    "text": "cô chú có đồng ý cùng tôi khám phá bí quyết này không",
    "textdich": ""
  },
  {
    "start": 292.166,
    "end": 295.0,
    "text": "nếu có vậy thì chúng ta cùng bắt đầu ngay nhé bắt đầu",
    "textdich": ""
  },
  {
    "start": 295.033,
    "end": 298.3,
    "text": "phần 1/1 bột sắn dây là gì và vì SAO tốt Cho thận",
    "textdich": ""
  },
  {
    "start": 299.1,
    "end": 300.0,
    "text": "cô chú thân mến",
    "textdich": ""
  },
  {
    "start": 300.7,
    "end": 302.833,
    "text": "trước khi tôi hướng dẫn cách pha và uống bột sắn",
    "textdich": ""
  },
  {
    "start": 302.966,
    "end": 304.1,
    "text": "dây SAO Cho tốt Cho thận",
    "textdich": ""
  },
  {
    "start": 304.4,
    "end": 306.166,
    "text": "tôi muốn cô chú hiểu rõ hơn một chút",
    "textdich": ""
  },
  {
    "start": 306.9,
    "end": 308.366,
    "text": "bột sắn dây thật sự là gì",
    "textdich": ""
  },
  {
    "start": 308.733,
    "end": 309.9,
    "text": "có những thành phần nào đặc biệt",
    "textdich": ""
  },
  {
    "start": 310.366,
    "end": 312.766,
    "text": "và tại SAO nó lại được coi là thần dược Cho thận yếu",
    "textdich": ""
  },
  {
    "start": 313.133,
    "end": 314.4,
    "text": "tiểu đêm mất ngủ",
    "textdich": ""
  },
  {
    "start": 315.433,
    "end": 317.5,
    "text": "có thể nhiều cô chú nghe đến bột sắn dây",
    "textdich": ""
  },
  {
    "start": 317.566,
    "end": 320.333,
    "text": "thì nghĩ ngay đến món chè sắn dây mát lạnh vào mùa hè",
    "textdich": ""
  },
  {
    "start": 320.833,
    "end": 322.233,
    "text": "hay ly nước sắn dây trong suốt",
    "textdich": ""
  },
  {
    "start": 322.633,
    "end": 324.3,
    "text": "có vị thơm dịu nhẹ để giải khát",
    "textdich": ""
  },
  {
    "start": 324.8,
    "end": 325.6,
    "text": "nhưng thực Ra",
    "textdich": ""
  },
  {
    "start": 325.733,
    "end": 326.166,
    "text": "bột sắn",
    "textdich": ""
  },
  {
    "start": 326.166,
    "end": 328.433,
    "text": "dây không chỉ đơn thuần là một loại bột để nấu chè",
    "textdich": ""
  },
  {
    "start": 328.833,
    "end": 331.6,
    "text": "mà nó xuất phát từ một loại củ chính là củ sắn dây",
    "textdich": ""
  },
  {
    "start": 331.933,
    "end": 333.5,
    "text": "trong đông y còn gọi là cát căn",
    "textdich": ""
  },
  {
    "start": 334.4,
    "end": 336.133,
    "text": "từ xưa củ sắn dây đã được",
    "textdich": ""
  },
  {
    "start": 336.133,
    "end": 338.033,
    "text": "ghi trong nhiều tài liệu y học cổ truyền",
    "textdich": ""
  },
  {
    "start": 338.6,
    "end": 340.433,
    "text": "người xưa dùng rễ củ sắn dây phơi khô",
    "textdich": ""
  },
  {
    "start": 340.8,
    "end": 341.966,
    "text": "tán thành bột để làm thuốc",
    "textdich": ""
  },
  {
    "start": 342.5,
    "end": 343.766,
    "text": "trong y thư cắt căn",
    "textdich": ""
  },
  {
    "start": 343.833,
    "end": 346.1,
    "text": "được xếp vào nhóm thảo dược có công năng thanh nhiệt",
    "textdich": ""
  },
  {
    "start": 346.4,
    "end": 349.3,
    "text": "giải độc sinh Tân chỉ khát thấu Trần",
    "textdich": ""
  },
  {
    "start": 349.766,
    "end": 352.1,
    "text": "nghĩa là giúp cơ thể mát hơn bớt nóng trong",
    "textdich": ""
  },
  {
    "start": 352.4,
    "end": 353.7,
    "text": "giải được độc tố tích tụ",
    "textdich": ""
  },
  {
    "start": 354.133,
    "end": 355.133,
    "text": "làm cơ thể dễ chịu hơn",
    "textdich": ""
  },
  {
    "start": 355.733,
    "end": 357.733,
    "text": "đồng thời còn có tác dụng làm dịu các triệu chứng",
    "textdich": ""
  },
  {
    "start": 357.8,
    "end": 360.5,
    "text": "sốt Cao khát nước và đặc biệt là giải rượu",
    "textdich": ""
  },
  {
    "start": 361.533,
    "end": 363.4,
    "text": "bây giờ chúng ta thử đặt câu hỏi",
    "textdich": ""
  },
  {
    "start": 363.733,
    "end": 366.033,
    "text": "vậy những tác dụng này liên quan gì đến thận yếu",
    "textdich": ""
  },
  {
    "start": 366.333,
    "end": 368.166,
    "text": "tiểu đêm mất ngủ của cô chú",
    "textdich": ""
  },
  {
    "start": 369.133,
    "end": 371.5,
    "text": "câu trả lời là có liên quan mật thiết",
    "textdich": ""
  },
  {
    "start": 371.9,
    "end": 374.3,
    "text": "để tôi phân tích kỹ hơn Cho cô chú dễ hình dung",
    "textdich": ""
  },
  {
    "start": 375.033,
    "end": 376.8,
    "text": "BA khi thận của chúng ta yếu đi",
    "textdich": ""
  },
  {
    "start": 377.033,
    "end": 378.5,
    "text": "cơ thể dễ bị mất cân bằng",
    "textdich": ""
  },
  {
    "start": 378.833,
    "end": 381.166,
    "text": "có người bị nóng trong bứt rứt khó ngủ",
    "textdich": ""
  },
  {
    "start": 381.633,
    "end": 383.4,
    "text": "có người lại bị rối loạn tiểu tiện",
    "textdich": ""
  },
  {
    "start": 383.6,
    "end": 384.7,
    "text": "đi tiểu đêm nhiều lần",
    "textdich": ""
  },
  {
    "start": 385.033,
    "end": 386.033,
    "text": "có người lại thấy mệt mỏi",
    "textdich": ""
  },
  {
    "start": 386.533,
    "end": 387.9,
    "text": "khó tiêu chán ăn",
    "textdich": ""
  },
  {
    "start": 388.366,
    "end": 389.133,
    "text": "trong đó",
    "textdich": ""
  },
  {
    "start": 389.133,
    "end": 392.1,
    "text": "nóng trong và mất ngủ là 2 vấn đề đi kèm rất phổ biến",
    "textdich": ""
  },
  {
    "start": 392.633,
    "end": 395.4,
    "text": "thận vốn là cơ quan lọc và thải độc chính của cơ thể",
    "textdich": ""
  },
  {
    "start": 396.033,
    "end": 397.033,
    "text": "khi thận làm việc kém",
    "textdich": ""
  },
  {
    "start": 397.5,
    "end": 399.966,
    "text": "độc tố tích tụ lại sinh Ra tình trạng nóng",
    "textdich": ""
  },
  {
    "start": 400.4,
    "end": 401.433,
    "text": "khiến cơ thể khó chịu",
    "textdich": ""
  },
  {
    "start": 401.833,
    "end": 403.3,
    "text": "dẫn đến giấc ngủ chập chờn",
    "textdich": ""
  },
  {
    "start": 404.233,
    "end": 406.766,
    "text": "và đây chính là lúc bột sắn dây phát huy tác dụng",
    "textdich": ""
  },
  {
    "start": 407.366,
    "end": 409.566,
    "text": "bởi vì với tính chất thanh nhiệt giải độc",
    "textdich": ""
  },
  {
    "start": 409.833,
    "end": 412.333,
    "text": "bột sắn dây có thể giúp cơ thể mát hơn từ bên trong",
    "textdich": ""
  },
  {
    "start": 412.733,
    "end": 414.6,
    "text": "giảm gánh nặng Cho thận trong việc điều hòa",
    "textdich": ""
  },
  {
    "start": 414.733,
    "end": 415.533,
    "text": "nhiệt và thải độc",
    "textdich": ""
  },
  {
    "start": 415.733,
    "end": 417.1,
    "text": "cơ thể khi cơ thể mát dịu",
    "textdich": ""
  },
  {
    "start": 417.5,
    "end": 419.0,
    "text": "độc tố được hỗ trợ loại bỏ",
    "textdich": ""
  },
  {
    "start": 419.333,
    "end": 421.133,
    "text": "thì thận cũng được nghỉ ngơi phần nào",
    "textdich": ""
  },
  {
    "start": 421.7,
    "end": 424.566,
    "text": "nhờ vậy các triệu chứng như tiểu đêm mất ngủ",
    "textdich": ""
  },
  {
    "start": 424.933,
    "end": 426.3,
    "text": "mệt mỏi sẽ dần được cải thiện",
    "textdich": ""
  },
  {
    "start": 427.2,
    "end": 428.5,
    "text": "ngoài tác dụng trong đông y",
    "textdich": ""
  },
  {
    "start": 428.833,
    "end": 430.933,
    "text": "khoa học hiện đại ngày nay cũng đã nghiên cứu",
    "textdich": ""
  },
  {
    "start": 431.133,
    "end": 433.733,
    "text": "và phát hiện trong bột sắn dây có nhiều hoạt chất quý",
    "textdich": ""
  },
  {
    "start": 434.333,
    "end": 436.966,
    "text": "nổi bật nhất là sắn dây BA puerarin",
    "textdich": ""
  },
  {
    "start": 437.166,
    "end": 439.4,
    "text": "đây là một hoạt chất thuộc nhóm isoflavon",
    "textdich": ""
  },
  {
    "start": 439.766,
    "end": 441.033,
    "text": "có tác dụng chống oxy hóa",
    "textdich": ""
  },
  {
    "start": 441.533,
    "end": 442.366,
    "text": "bảo vệ tế bào",
    "textdich": ""
  },
  {
    "start": 442.9,
    "end": 444.566,
    "text": "đặc biệt tốt Cho Tim mạch và thận",
    "textdich": ""
  },
  {
    "start": 445.133,
    "end": 447.366,
    "text": "puerarin giúp cải thiện tuần hoàn máu",
    "textdich": ""
  },
  {
    "start": 447.5,
    "end": 449.433,
    "text": "làm giảm áp lực Cho hệ thống lọc của thận",
    "textdich": ""
  },
  {
    "start": 449.9,
    "end": 452.033,
    "text": "nhờ đó bảo vệ chức năng thận 6",
    "textdich": ""
  },
  {
    "start": 452.433,
    "end": 454.833,
    "text": "isoflavone đây là nhóm hợp chất thực vật",
    "textdich": ""
  },
  {
    "start": 454.9,
    "end": 456.2,
    "text": "có khả năng điều hòa hormone",
    "textdich": ""
  },
  {
    "start": 456.6,
    "end": 457.566,
    "text": "làm dịu thần kinh",
    "textdich": ""
  },
  {
    "start": 458.0,
    "end": 460.5,
    "text": "giúp giảm căng thẳng từ đó giúp ngủ ngon hơn",
    "textdich": ""
  },
  {
    "start": 461.166,
    "end": 462.933,
    "text": "với người thận yếu thường hay mất ngủ",
    "textdich": ""
  },
  {
    "start": 463.366,
    "end": 464.1,
    "text": "căng thẳng",
    "textdich": ""
  },
  {
    "start": 464.1,
    "end": 467.4,
    "text": "thì isoflavone trong bột sắn dây có thể hỗ trợ rất tốt",
    "textdich": ""
  },
  {
    "start": 468.033,
    "end": 470.366,
    "text": "BA genistein một hợp chất nổi bật khác",
    "textdich": ""
  },
  {
    "start": 470.633,
    "end": 471.633,
    "text": "có tác dụng kháng viêm",
    "textdich": ""
  },
  {
    "start": 472.0,
    "end": 472.8,
    "text": "chống lão hóa",
    "textdich": ""
  },
  {
    "start": 473.033,
    "end": 475.7,
    "text": "giúp ngăn chặn tổn thương các mạch máu nhỏ trong thận",
    "textdich": ""
  },
  {
    "start": 476.3,
    "end": 477.1,
    "text": "điều này rất quan trọng",
    "textdich": ""
  },
  {
    "start": 477.6,
    "end": 478.6,
    "text": "bởi vì thận yếu là",
    "textdich": ""
  },
  {
    "start": 478.6,
    "end": 480.833,
    "text": "do các VI mạch trong cầu thận bị tổn thương dần",
    "textdich": ""
  },
  {
    "start": 480.933,
    "end": 481.733,
    "text": "Theo thời gian",
    "textdich": ""
  },
  {
    "start": 482.533,
    "end": 483.366,
    "text": "cô chú thấy đó",
    "textdich": ""
  },
  {
    "start": 483.5,
    "end": 484.3,
    "text": "bột sắn dây",
    "textdich": ""
  },
  {
    "start": 484.4,
    "end": 486.8,
    "text": "không chỉ đơn giản là một loại bột để nấu chè giải khát",
    "textdich": ""
  },
  {
    "start": 487.166,
    "end": 487.633,
    "text": "mà ẩn",
    "textdich": ""
  },
  {
    "start": 487.633,
    "end": 489.933,
    "text": "bên trong nó là cả một kho báu dưỡng chất tự nhiên",
    "textdich": ""
  },
  {
    "start": 490.433,
    "end": 492.766,
    "text": "có thể giúp bảo vệ thận hỗ trợ tuần hoàn",
    "textdich": ""
  },
  {
    "start": 493.2,
    "end": 495.033,
    "text": "giảm nóng trong cải thiện giấc ngủ",
    "textdich": ""
  },
  {
    "start": 496.1,
    "end": 498.366,
    "text": "một điểm nữa tôi muốn nhấn mạnh trong đông y",
    "textdich": ""
  },
  {
    "start": 498.633,
    "end": 500.933,
    "text": "bột sắn dây còn có tác dụng lợi tiểu nhẹ",
    "textdich": ""
  },
  {
    "start": 501.4,
    "end": 502.3,
    "text": "với người thận yếu",
    "textdich": ""
  },
  {
    "start": 502.6,
    "end": 504.9,
    "text": "chức năng điều tiết nước trong cơ thể bị rối loạn",
    "textdich": ""
  },
  {
    "start": 505.233,
    "end": 508.033,
    "text": "dễ gây phù nề chân Tay hay tiểu đêm nhiều lần",
    "textdich": ""
  },
  {
    "start": 508.6,
    "end": 510.166,
    "text": "khi uống bột sắn dây đúng cách",
    "textdich": ""
  },
  {
    "start": 510.433,
    "end": 511.733,
    "text": "tác dụng lợi tiểu nhẹ nhàng",
    "textdich": ""
  },
  {
    "start": 511.933,
    "end": 513.533,
    "text": "sẽ giúp cơ thể cân bằng lại lượng dịch",
    "textdich": ""
  },
  {
    "start": 513.833,
    "end": 515.233,
    "text": "không còn tình trạng ứ đọng nước",
    "textdich": ""
  },
  {
    "start": 515.7,
    "end": 517.233,
    "text": "khi cơ thể điều hòa được nước tiểu",
    "textdich": ""
  },
  {
    "start": 517.566,
    "end": 518.933,
    "text": "thận đỡ phải làm việc quá sức",
    "textdich": ""
  },
  {
    "start": 519.2,
    "end": 521.133,
    "text": "từ đó triệu chứng tiểu đêm cũng giảm dần",
    "textdich": ""
  },
  {
    "start": 522.0,
    "end": 523.8,
    "text": "tóm lại để cô chú dễ nhớ",
    "textdich": ""
  },
  {
    "start": 524.166,
    "end": 525.8,
    "text": "bột sắn dây tốt Cho thận bởi vì",
    "textdich": ""
  },
  {
    "start": 526.733,
    "end": 529.766,
    "text": "4 thanh nhiệt giải độc giúp cơ thể mát hơn",
    "textdich": ""
  },
  {
    "start": 530.233,
    "end": 532.4,
    "text": "giảm nóng trong giảm gánh nặng Cho thận",
    "textdich": ""
  },
  {
    "start": 533.233,
    "end": 536.4,
    "text": "lợi tiểu nhẹ hỗ trợ điều hòa nước giảm phù nề",
    "textdich": ""
  },
  {
    "start": 536.8,
    "end": 537.6,
    "text": "giảm tiểu đêm",
    "textdich": ""
  },
  {
    "start": 538.433,
    "end": 539.333,
    "text": "chống oxy hóa",
    "textdich": ""
  },
  {
    "start": 539.8,
    "end": 541.333,
    "text": "bảo vệ mạch máu nhỏ trong thận",
    "textdich": ""
  },
  {
    "start": 541.6,
    "end": 543.1,
    "text": "ngăn ngừa tổn thương tiến triển",
    "textdich": ""
  },
  {
    "start": 543.4,
    "end": 544.766,
    "text": "hỗ trợ thận hoạt động tốt hơn",
    "textdich": ""
  },
  {
    "start": 545.5,
    "end": 546.9,
    "text": "4 điều hòa thần kinh",
    "textdich": ""
  },
  {
    "start": 547.233,
    "end": 548.033,
    "text": "cải thiện giấc ngủ",
    "textdich": ""
  },
  {
    "start": 548.4,
    "end": 551.533,
    "text": "người thận yếu thường mất ngủ bột sắn dây giúp ngủ sâu",
    "textdich": ""
  },
  {
    "start": 552.0,
    "end": 552.8,
    "text": "ngủ ngon hơn",
    "textdich": ""
  },
  {
    "start": 553.3,
    "end": 556.3,
    "text": "2 cô chú thử hình dung mỗi tối trước khi đi ngủ",
    "textdich": ""
  },
  {
    "start": 556.633,
    "end": 559.166,
    "text": "thay vì uống ly trà đặc hay cà phê khiến khó ngủ",
    "textdich": ""
  },
  {
    "start": 559.566,
    "end": 562.0,
    "text": "cô chú chỉ cần uống một ly sắn dây pha đúng cách",
    "textdich": ""
  },
  {
    "start": 562.433,
    "end": 564.4,
    "text": "cơ thể được thanh mát thận được hỗ trợ",
    "textdich": ""
  },
  {
    "start": 564.766,
    "end": 565.633,
    "text": "tinh thần thư thái",
    "textdich": ""
  },
  {
    "start": 566.133,
    "end": 568.233,
    "text": "và cô chú dễ dàng đi vào giấc ngủ sâu",
    "textdich": ""
  },
  {
    "start": 568.766,
    "end": 569.766,
    "text": "chỉ một thay đổi nhỏ",
    "textdich": ""
  },
  {
    "start": 570.2,
    "end": 571.933,
    "text": "nhưng lại mang đến một kết quả rất lớn",
    "textdich": ""
  },
  {
    "start": 573.0,
    "end": 573.8,
    "text": "chính vì vậy",
    "textdich": ""
  },
  {
    "start": 573.9,
    "end": 576.0,
    "text": "tôi thường nói với nhiều bệnh nhân lớn tuổi rằng",
    "textdich": ""
  },
  {
    "start": 576.333,
    "end": 578.766,
    "text": "bột sắn dây không chỉ là một món giải khát bình thường",
    "textdich": ""
  },
  {
    "start": 579.133,
    "end": 580.333,
    "text": "mà là một người bạn của thận",
    "textdich": ""
  },
  {
    "start": 580.766,
    "end": 582.633,
    "text": "nếu mình biết trân trọng và dùng đúng cách",
    "textdich": ""
  },
  {
    "start": 582.933,
    "end": 584.2,
    "text": "nó sẽ giúp thận được bảo vệ",
    "textdich": ""
  },
  {
    "start": 584.733,
    "end": 587.2,
    "text": "giúp cô chú thoát khỏi cảnh phải tiểu đêm nhiều lần",
    "textdich": ""
  },
  {
    "start": 587.6,
    "end": 589.333,
    "text": "ngủ ngon giấc và có thêm sức khỏe",
    "textdich": ""
  },
  {
    "start": 589.5,
    "end": 591.233,
    "text": "để tận hưởng tuổi già bên con cháu",
    "textdich": ""
  },
  {
    "start": 591.433,
    "end": 591.766,
    "text": "của mình",
    "textdich": ""
  },
  {
    "start": 591.766,
    "end": 595.0,
    "text": "4/2 lợi ích của bột sắn dây đối với người thận yếu",
    "textdich": ""
  },
  {
    "start": 595.9,
    "end": 596.8,
    "text": "cô chú thân mến",
    "textdich": ""
  },
  {
    "start": 597.4,
    "end": 598.633,
    "text": "khi nhắc đến bột sắn dây",
    "textdich": ""
  },
  {
    "start": 599.1,
    "end": 601.166,
    "text": "chắc hẳn nhiều người nghĩ ngay đến một loại bột mát",
    "textdich": ""
  },
  {
    "start": 601.533,
    "end": 603.833,
    "text": "hay dùng để pha nước uống giải khát vào mùa hè",
    "textdich": ""
  },
  {
    "start": 604.4,
    "end": 606.833,
    "text": "nhưng ít AI biết rằng nếu biết cách dùng đúng",
    "textdich": ""
  },
  {
    "start": 607.166,
    "end": 609.333,
    "text": "bột sắn dây lại trở thành một người bạn đồng hành",
    "textdich": ""
  },
  {
    "start": 609.5,
    "end": 610.333,
    "text": "vô cùng quý giá",
    "textdich": ""
  },
  {
    "start": 610.433,
    "end": 612.2,
    "text": "Cho những AI đang gặp tình trạng thận yếu",
    "textdich": ""
  },
  {
    "start": 612.533,
    "end": 614.933,
    "text": "tiểu đêm mất ngủ hoặc cơ thể suy nhược",
    "textdich": ""
  },
  {
    "start": 615.4,
    "end": 616.633,
    "text": "ở phần trước tôi đã",
    "textdich": ""
  },
  {
    "start": 616.633,
    "end": 618.333,
    "text": "chia sẻ cùng cô chú về nguồn gốc",
    "textdich": ""
  },
  {
    "start": 618.433,
    "end": 619.833,
    "text": "cũng như giá trị của bột sắn dây",
    "textdich": ""
  },
  {
    "start": 620.4,
    "end": 622.633,
    "text": "bây giờ tôi Xin đi sâu hơn vào lợi ích",
    "textdich": ""
  },
  {
    "start": 622.766,
    "end": 624.966,
    "text": "thực sự của loại bột này đối với người có chức năng",
    "textdich": ""
  },
  {
    "start": 625.033,
    "end": 625.833,
    "text": "thận suy giảm",
    "textdich": ""
  },
  {
    "start": 626.7,
    "end": 629.2,
    "text": "một bột sắn dây giúp ngăn ngừa suy thận",
    "textdich": ""
  },
  {
    "start": 629.633,
    "end": 632.6,
    "text": "cô ơi cô chú biết không khi bước sang tuổi 60",
    "textdich": ""
  },
  {
    "start": 632.9,
    "end": 634.0,
    "text": "chức năng của cẩu thận",
    "textdich": ""
  },
  {
    "start": 634.133,
    "end": 635.766,
    "text": "tức là bộ phận lọc máu trong thận",
    "textdich": ""
  },
  {
    "start": 636.0,
    "end": 636.833,
    "text": "bắt đầu suy giảm",
    "textdich": ""
  },
  {
    "start": 637.533,
    "end": 639.166,
    "text": "mỗi ngày thận phải làm nhiệm vụ",
    "textdich": ""
  },
  {
    "start": 639.3,
    "end": 641.766,
    "text": "lọc hàng trăm lít máu để loại bỏ chất cặn bã",
    "textdich": ""
  },
  {
    "start": 642.166,
    "end": 642.966,
    "text": "độc tố Ra ngoài",
    "textdich": ""
  },
  {
    "start": 643.533,
    "end": 644.333,
    "text": "nếu quá tải",
    "textdich": ""
  },
  {
    "start": 644.7,
    "end": 647.5,
    "text": "thận dễ bị tổn thương lâu dần dẫn đến suy thận",
    "textdich": ""
  },
  {
    "start": 648.366,
    "end": 650.533,
    "text": "bột sắn dây lại chứa nhiều puerarin",
    "textdich": ""
  },
  {
    "start": 650.833,
    "end": 652.833,
    "text": "isoflavon và genistein",
    "textdich": ""
  },
  {
    "start": 652.966,
    "end": 654.333,
    "text": "những hoạt chất giúp làm mát cơ thể",
    "textdich": ""
  },
  {
    "start": 654.933,
    "end": 656.966,
    "text": "giảm tình trạng viêm nhẹ và hỗ trợ thải độc",
    "textdich": ""
  },
  {
    "start": 657.533,
    "end": 660.166,
    "text": "khi cơ thể ít nóng trong ít tích tụ độc tố",
    "textdich": ""
  },
  {
    "start": 660.566,
    "end": 661.766,
    "text": "thận sẽ giảm gánh nặng",
    "textdich": ""
  },
  {
    "start": 662.033,
    "end": 664.133,
    "text": "từ đó làm chậm lại quá trình suy thoái",
    "textdich": ""
  },
  {
    "start": 664.566,
    "end": 666.966,
    "text": "tôi thường ví bột sắn dây giống như một người hỗ trợ",
    "textdich": ""
  },
  {
    "start": 667.033,
    "end": 669.766,
    "text": "âm thầm đứng phía sau để đỡ bớt công việc Cho thận",
    "textdich": ""
  },
  {
    "start": 670.133,
    "end": 671.833,
    "text": "giúp thận không phải gắng sức quá nhiều",
    "textdich": ""
  },
  {
    "start": 672.533,
    "end": 675.9,
    "text": "một 2 giảm tiểu đêm bàng quang bớt kích thích",
    "textdich": ""
  },
  {
    "start": 676.7,
    "end": 678.166,
    "text": "một trong những nỗi khổ lớn nhất",
    "textdich": ""
  },
  {
    "start": 678.233,
    "end": 680.433,
    "text": "mà người thận yếu phải chịu chính là tiểu đêm",
    "textdich": ""
  },
  {
    "start": 680.533,
    "end": 683.733,
    "text": "nhiều lần mỗi đêm cô chú phải thức dậy 2 đến BA lần",
    "textdich": ""
  },
  {
    "start": 684.133,
    "end": 685.633,
    "text": "thậm chí có người năm đến 6 lần",
    "textdich": ""
  },
  {
    "start": 686.166,
    "end": 688.433,
    "text": "giấc ngủ bị gián đoạn khiến sáng Ra mệt mỏi",
    "textdich": ""
  },
  {
    "start": 688.8,
    "end": 689.966,
    "text": "HOA mắt chóng mặt",
    "textdich": ""
  },
  {
    "start": 690.433,
    "end": 692.8,
    "text": "4 bột sắn dây với tính mát thanh nhiệt",
    "textdich": ""
  },
  {
    "start": 693.1,
    "end": 694.9,
    "text": "có khả năng cân bằng dịch thể trong cơ thể",
    "textdich": ""
  },
  {
    "start": 695.366,
    "end": 697.833,
    "text": "từ đó giúp bàng quang không bị kích thích quá mức",
    "textdich": ""
  },
  {
    "start": 698.3,
    "end": 699.333,
    "text": "khi cơ thể bớt nóng",
    "textdich": ""
  },
  {
    "start": 699.633,
    "end": 700.4,
    "text": "bớt khô",
    "textdich": ""
  },
  {
    "start": 700.4,
    "end": 702.933,
    "text": "thì nước tiểu cũng không bị tạo Ra nhiều vào ban đêm",
    "textdich": ""
  },
  {
    "start": 703.633,
    "end": 704.566,
    "text": "nói một cách dễ hiểu",
    "textdich": ""
  },
  {
    "start": 704.8,
    "end": 705.633,
    "text": "uống bột sắn dây",
    "textdich": ""
  },
  {
    "start": 705.766,
    "end": 706.9,
    "text": "đúng cách có thể giúp ổn định",
    "textdich": ""
  },
  {
    "start": 706.966,
    "end": 708.7,
    "text": "nhịp sinh học Cho thận và bàng quang",
    "textdich": ""
  },
  {
    "start": 709.033,
    "end": 710.533,
    "text": "từ đó giảm số lần tiểu đêm",
    "textdich": ""
  },
  {
    "start": 711.0,
    "end": 712.2,
    "text": "giúp cô chú ngủ yên hơn",
    "textdich": ""
  },
  {
    "start": 713.2,
    "end": 715.9,
    "text": "BA giúp ngủ sâu giấc bớt mệt mỏi",
    "textdich": ""
  },
  {
    "start": 716.766,
    "end": 718.5,
    "text": "người thận yếu thường bị khó ngủ",
    "textdich": ""
  },
  {
    "start": 718.933,
    "end": 720.7,
    "text": "ngủ chập chờn hoặc hay mơ nhiều",
    "textdich": ""
  },
  {
    "start": 721.3,
    "end": 723.4,
    "text": "nguyên nhân là do sự mất cân bằng giữa âm",
    "textdich": ""
  },
  {
    "start": 723.7,
    "end": 724.566,
    "text": "dương trong cơ thể",
    "textdich": ""
  },
  {
    "start": 724.966,
    "end": 726.3,
    "text": "cộng thêm tình trạng nóng trong",
    "textdich": ""
  },
  {
    "start": 726.7,
    "end": 728.166,
    "text": "khiến thần kinh khó thư giãn",
    "textdich": ""
  },
  {
    "start": 728.833,
    "end": 729.8,
    "text": "4 trong đông y",
    "textdich": ""
  },
  {
    "start": 730.1,
    "end": 732.366,
    "text": "bột sắn dây được xem là vị thuốc giúp thanh nhiệt",
    "textdich": ""
  },
  {
    "start": 732.633,
    "end": 733.5,
    "text": "làm dịu cơ thể",
    "textdich": ""
  },
  {
    "start": 733.9,
    "end": 735.133,
    "text": "hạ căng thẳng thần kinh",
    "textdich": ""
  },
  {
    "start": 735.733,
    "end": 737.4,
    "text": "khi cô chú uống một ly nước bột sắn",
    "textdich": ""
  },
  {
    "start": 737.5,
    "end": 739.8,
    "text": "dây mát lạnh trước bữa ăn hoặc vào buổi chiều tối",
    "textdich": ""
  },
  {
    "start": 740.333,
    "end": 741.9,
    "text": "cảm giác thanh mát sẽ LAN tỏa",
    "textdich": ""
  },
  {
    "start": 742.233,
    "end": 744.533,
    "text": "giúp cơ thể dễ chịu đầu óc nhẹ nhàng",
    "textdich": ""
  },
  {
    "start": 744.9,
    "end": 746.733,
    "text": "từ đó dễ bước vào giấc ngủ sâu hơn",
    "textdich": ""
  },
  {
    "start": 747.3,
    "end": 749.366,
    "text": "4 một giấc ngủ ngon không chỉ cải thiện tinh thần",
    "textdich": ""
  },
  {
    "start": 749.833,
    "end": 752.333,
    "text": "mà còn giúp thận có thời gian nghỉ ngơi và hồi phục",
    "textdich": ""
  },
  {
    "start": 753.2,
    "end": 756.766,
    "text": "4 hỗ trợ tiêu hóa giúp cơ thể khỏe tổng thể",
    "textdich": ""
  },
  {
    "start": 757.4,
    "end": 759.9,
    "text": "thứ nhất có thể cô chú chưa biết khi thận yếu",
    "textdich": ""
  },
  {
    "start": 760.233,
    "end": 762.633,
    "text": "hệ tiêu hóa và Tim mạch cũng thường bị ảnh hưởng",
    "textdich": ""
  },
  {
    "start": 763.4,
    "end": 765.5,
    "text": "người thận yếu dễ gặp tình trạng ăn không ngon",
    "textdich": ""
  },
  {
    "start": 765.833,
    "end": 768.533,
    "text": "bụng đầy chướng táo bón hoặc tiêu chảy 7 thường",
    "textdich": ""
  },
  {
    "start": 769.4,
    "end": 772.333,
    "text": "bột sắn dây có đặc tính dịu nhẹ hỗ trợ tiêu hóa",
    "textdich": ""
  },
  {
    "start": 772.766,
    "end": 775.4,
    "text": "giúp giảm đầy bụng mát ruột nhuận tràng",
    "textdich": ""
  },
  {
    "start": 775.9,
    "end": 777.5,
    "text": "khi tiêu hóa hoạt động trơn TRU",
    "textdich": ""
  },
  {
    "start": 777.9,
    "end": 779.5,
    "text": "cơ thể hấp thu dinh dưỡng tốt hơn",
    "textdich": ""
  },
  {
    "start": 780.0,
    "end": 781.233,
    "text": "từ đó cung cấp năng lượng",
    "textdich": ""
  },
  {
    "start": 781.333,
    "end": 783.0,
    "text": "và chất cần thiết Cho thận hoạt động",
    "textdich": ""
  },
  {
    "start": 783.6,
    "end": 785.766,
    "text": "ngoài Ra trong một số nghiên cứu hiện đại",
    "textdich": ""
  },
  {
    "start": 786.1,
    "end": 787.633,
    "text": "bột sắn dây còn được ghi nhận",
    "textdich": ""
  },
  {
    "start": 787.733,
    "end": 789.233,
    "text": "có khả năng giúp ổn định huyết áp",
    "textdich": ""
  },
  {
    "start": 789.633,
    "end": 790.566,
    "text": "bảo vệ mạch máu",
    "textdich": ""
  },
  {
    "start": 791.1,
    "end": 792.1,
    "text": "khi Tim mạch khỏe",
    "textdich": ""
  },
  {
    "start": 792.433,
    "end": 793.5,
    "text": "máu lưu thông đều đặn",
    "textdich": ""
  },
  {
    "start": 793.766,
    "end": 795.533,
    "text": "thận cũng sẽ được nuôi dưỡng tốt hơn",
    "textdich": ""
  },
  {
    "start": 796.2,
    "end": 799.366,
    "text": "4 năm dán tiếp bảo vệ thận và toàn cơ thể",
    "textdich": ""
  },
  {
    "start": 800.333,
    "end": 803.0,
    "text": "cô chú thấy đó những lợi ích như ngăn suy thận",
    "textdich": ""
  },
  {
    "start": 803.233,
    "end": 804.033,
    "text": "giảm tiểu đêm",
    "textdich": ""
  },
  {
    "start": 804.333,
    "end": 805.133,
    "text": "cải thiện giấc ngủ",
    "textdich": ""
  },
  {
    "start": 805.533,
    "end": 806.333,
    "text": "hỗ trợ tiêu hóa",
    "textdich": ""
  },
  {
    "start": 806.766,
    "end": 809.833,
    "text": "bảo vệ Tim mạch tất cả đều liên quan chặt chẽ với nhau",
    "textdich": ""
  },
  {
    "start": 810.366,
    "end": 812.3,
    "text": "một cơ thể khỏe tổng thể chính là nền tảng",
    "textdich": ""
  },
  {
    "start": 812.4,
    "end": 814.366,
    "text": "để thận không phải chịu áp lực quá lớn",
    "textdich": ""
  },
  {
    "start": 814.9,
    "end": 817.133,
    "text": "năm có rất nhiều cô chú chia sẻ với tôi rằng",
    "textdich": ""
  },
  {
    "start": 817.233,
    "end": 819.333,
    "text": "sau một thời gian kiên trì uống bột sắn dây",
    "textdich": ""
  },
  {
    "start": 819.7,
    "end": 822.1,
    "text": "cơ thể trở nên nhẹ nhõm hơn ngủ ngon hơn",
    "textdich": ""
  },
  {
    "start": 822.4,
    "end": 823.5,
    "text": "bớt đi tiểu đêm",
    "textdich": ""
  },
  {
    "start": 823.8,
    "end": 825.6,
    "text": "và quan trọng là tinh thần cũng thoải mái",
    "textdich": ""
  },
  {
    "start": 826.0,
    "end": 829.366,
    "text": "vui vẻ hơn tôi tin rằng khi tinh thần đã ổn định",
    "textdich": ""
  },
  {
    "start": 829.7,
    "end": 831.633,
    "text": "thận cũng sẽ được chăm sóc một cách tự nhiên",
    "textdich": ""
  },
  {
    "start": 831.733,
    "end": 832.533,
    "text": "từ bên trong",
    "textdich": ""
  },
  {
    "start": 833.233,
    "end": 835.733,
    "text": "cô chú thân mến bột sắn dây tuy dân dã",
    "textdich": ""
  },
  {
    "start": 836.166,
    "end": 838.433,
    "text": "rẻ tiền nhưng lại ẩn chứa những lợi ích",
    "textdich": ""
  },
  {
    "start": 838.6,
    "end": 840.2,
    "text": "vô cùng quý giá Cho người thân yếu",
    "textdich": ""
  },
  {
    "start": 840.8,
    "end": 842.966,
    "text": "tôi không nói rằng bột sắn dây là thuốc tiên",
    "textdich": ""
  },
  {
    "start": 843.1,
    "end": 844.733,
    "text": "có thể chữa khỏi hoàn toàn bệnh thận",
    "textdich": ""
  },
  {
    "start": 845.233,
    "end": 847.433,
    "text": "nhưng tôi tin rằng nếu biết cách dùng đúng",
    "textdich": ""
  },
  {
    "start": 847.833,
    "end": 849.766,
    "text": "kết hợp cùng chế độ sinh hoạt lành mạnh",
    "textdich": ""
  },
  {
    "start": 850.133,
    "end": 851.8,
    "text": "thì đây sẽ là một giải pháp an toàn",
    "textdich": ""
  },
  {
    "start": 852.3,
    "end": 854.3,
    "text": "tự nhiên và hiệu quả để hỗ trợ thận",
    "textdich": ""
  },
  {
    "start": 855.2,
    "end": 856.033,
    "text": "trong phần tiếp Theo",
    "textdich": ""
  },
  {
    "start": 856.433,
    "end": 858.833,
    "text": "tôi sẽ hướng dẫn cô chú cách pha và uống bột sắn",
    "textdich": ""
  },
  {
    "start": 859.0,
    "end": 859.8,
    "text": "dây chuẩn nhất",
    "textdich": ""
  },
  {
    "start": 859.9,
    "end": 861.166,
    "text": "kèm Theo những lưu ý quan trọng",
    "textdich": ""
  },
  {
    "start": 861.3,
    "end": 862.633,
    "text": "để phát huy tối đa lợi ích",
    "textdich": ""
  },
  {
    "start": 862.8,
    "end": 864.5,
    "text": "và tránh tác dụng phụ không mong muốn",
    "textdich": ""
  },
  {
    "start": 865.166,
    "end": 868.233,
    "text": "2/3 cách dùng bột sắn dây đúng chuẩn Cho thận",
    "textdich": ""
  },
  {
    "start": 869.0,
    "end": 869.8,
    "text": "ở những phần trước",
    "textdich": ""
  },
  {
    "start": 870.033,
    "end": 870.833,
    "text": "tôi đã chia sẻ",
    "textdich": ""
  },
  {
    "start": 870.966,
    "end": 872.766,
    "text": "cùng cô chú về giá trị của bột sắn",
    "textdich": ""
  },
  {
    "start": 872.9,
    "end": 873.7,
    "text": "dây đối với sức khỏe",
    "textdich": ""
  },
  {
    "start": 874.3,
    "end": 876.8,
    "text": "đặc biệt là với những người thận yếu hay tiểu đêm",
    "textdich": ""
  },
  {
    "start": 877.166,
    "end": 878.8,
    "text": "khó ngủ bây giờ",
    "textdich": ""
  },
  {
    "start": 878.966,
    "end": 881.433,
    "text": "tôi Xin đi sâu vào phần thực tế và quan trọng nhất",
    "textdich": ""
  },
  {
    "start": 881.733,
    "end": 884.833,
    "text": "cách pha bột sắn dây để uống SAO Cho an toàn hiệu quả",
    "textdich": ""
  },
  {
    "start": 885.4,
    "end": 886.8,
    "text": "trong đó cách pha chín",
    "textdich": ""
  },
  {
    "start": 886.9,
    "end": 888.566,
    "text": "là phương pháp được tôi khuyên dùng nhiều nhất",
    "textdich": ""
  },
  {
    "start": 888.933,
    "end": 890.0,
    "text": "vì vừa dễ thực hiện",
    "textdich": ""
  },
  {
    "start": 890.366,
    "end": 891.3,
    "text": "vừa đảm bảo vệ sinh",
    "textdich": ""
  },
  {
    "start": 891.8,
    "end": 893.133,
    "text": "lại phù hợp với hệ tiêu hóa",
    "textdich": ""
  },
  {
    "start": 893.233,
    "end": 894.566,
    "text": "và cơ thể của người Cao tuổi",
    "textdich": ""
  },
  {
    "start": 895.366,
    "end": 897.233,
    "text": "6 vì SAO nên chọn cách pha chín",
    "textdich": ""
  },
  {
    "start": 898.133,
    "end": 900.533,
    "text": "có nhiều người thường quen uống bột sắn dây sống",
    "textdich": ""
  },
  {
    "start": 900.8,
    "end": 903.1,
    "text": "chỉ hòa tan với nước nguội và thêm chút đường",
    "textdich": ""
  },
  {
    "start": 903.633,
    "end": 906.233,
    "text": "tuy nhiên với người thận yếu hoặc người Cao tuổi",
    "textdich": ""
  },
  {
    "start": 906.6,
    "end": 908.8,
    "text": "uống sống lại tiềm ẩn một số rủi ro",
    "textdich": ""
  },
  {
    "start": 909.166,
    "end": 910.533,
    "text": "khó tiêu lạnh bụng",
    "textdich": ""
  },
  {
    "start": 910.9,
    "end": 912.566,
    "text": "dễ gây đau bụng hoặc tiêu chảy",
    "textdich": ""
  },
  {
    "start": 913.166,
    "end": 914.333,
    "text": "BA khi pha chín",
    "textdich": ""
  },
  {
    "start": 914.6,
    "end": 917.966,
    "text": "bột sắn dây sẽ được nấu thành dạng hổ trong sánh mịn",
    "textdich": ""
  },
  {
    "start": 918.433,
    "end": 920.933,
    "text": "điều này vừa giúp loại bỏ VI khuẩn tạp chất",
    "textdich": ""
  },
  {
    "start": 921.233,
    "end": 922.833,
    "text": "vừa giúp cơ thể dễ hấp thu hơn",
    "textdich": ""
  },
  {
    "start": 923.233,
    "end": 925.733,
    "text": "lại không gây kích ứng Cho dạ dày ruột",
    "textdich": ""
  },
  {
    "start": 926.233,
    "end": 929.3,
    "text": "vì thế tôi luôn khuyên cô chú muốn an toàn",
    "textdich": ""
  },
  {
    "start": 929.8,
    "end": 931.133,
    "text": "hãy pha chín bột sắn dây",
    "textdich": ""
  },
  {
    "start": 932.1,
    "end": 933.8,
    "text": "cách pha chín bột sắn dây chuẩn nhất",
    "textdich": ""
  },
  {
    "start": 934.6,
    "end": 936.6,
    "text": "để pha một cốc bột sắn dây chín ngon",
    "textdich": ""
  },
  {
    "start": 936.966,
    "end": 938.566,
    "text": "mát và tốt Cho sức khỏe thận",
    "textdich": ""
  },
  {
    "start": 938.933,
    "end": 940.7,
    "text": "cô chú có thể làm Theo các bước sau",
    "textdich": ""
  },
  {
    "start": 941.366,
    "end": 942.7,
    "text": "bước một chuẩn bị nguyên liệu",
    "textdich": ""
  },
  {
    "start": 943.566,
    "end": 946.433,
    "text": "một muỗng bột sắn dây khoảng 10 đến 15 giờ",
    "textdich": ""
  },
  {
    "start": 947.3,
    "end": 949.3,
    "text": "200 mi li lít nước sôi nóng giả",
    "textdich": ""
  },
  {
    "start": 950.2,
    "end": 953.1,
    "text": "một đến 2 lát chanh tươi hoặc vài giọt nước cốt chanh",
    "textdich": ""
  },
  {
    "start": 953.933,
    "end": 955.833,
    "text": "một ít đường phèn tùy khẩu vị",
    "textdich": ""
  },
  {
    "start": 956.166,
    "end": 957.9,
    "text": "có thể không dùng nếu muốn uống nguyên chất",
    "textdich": ""
  },
  {
    "start": 958.733,
    "end": 962.1,
    "text": "cách thực hiện sau đó Cho bột sắn dây vào ly thủy tinh",
    "textdich": ""
  },
  {
    "start": 963.0,
    "end": 965.966,
    "text": "rót từ từ nước sôi vào đồng thời khuấy đều Tay",
    "textdich": ""
  },
  {
    "start": 966.833,
    "end": 968.766,
    "text": "khi khuấy cô chú sẽ thấy bột sắn",
    "textdich": ""
  },
  {
    "start": 968.9,
    "end": 971.433,
    "text": "dây dần dần chuyển từ dạng bột trắng sang dạng trong",
    "textdich": ""
  },
  {
    "start": 971.566,
    "end": 973.1,
    "text": "sánh mịn dẻo như hồ",
    "textdich": ""
  },
  {
    "start": 973.933,
    "end": 976.8,
    "text": "và cuối cùng thêm vài giọt chanh hoặc chút đường phèn",
    "textdich": ""
  },
  {
    "start": 976.966,
    "end": 977.766,
    "text": "để tăng hương vị",
    "textdich": ""
  },
  {
    "start": 978.1,
    "end": 979.366,
    "text": "rồi khuấy đều một lần nữa",
    "textdich": ""
  },
  {
    "start": 979.9,
    "end": 983.7,
    "text": "cách uống uống khi còn ấm không để nguội hẳn 4",
    "textdich": ""
  },
  {
    "start": 983.966,
    "end": 985.7,
    "text": "thời điểm tốt nhất là vào buổi tối",
    "textdich": ""
  },
  {
    "start": 986.033,
    "end": 987.8,
    "text": "trước khi đi ngủ khoảng một đến 2 tiếng",
    "textdich": ""
  },
  {
    "start": 988.433,
    "end": 991.3,
    "text": "lúc này cơ thể vừa hấp thu được tinh chất trong bột",
    "textdich": ""
  },
  {
    "start": 991.6,
    "end": 992.833,
    "text": "vừa tạo cảm giác nhẹ nhàng",
    "textdich": ""
  },
  {
    "start": 993.4,
    "end": 994.2,
    "text": "dễ ngủ",
    "textdich": ""
  },
  {
    "start": 994.933,
    "end": 997.133,
    "text": "lợi ích khi uống bột sắn dây pha chín",
    "textdich": ""
  },
  {
    "start": 997.7,
    "end": 1001.333,
    "text": "4 bảo vệ dạ dày đường ruột bột đã chín dễ tiêu hóa",
    "textdich": ""
  },
  {
    "start": 1001.7,
    "end": 1003.566,
    "text": "không gây lạnh bụng hay rối loạn tiêu hóa",
    "textdich": ""
  },
  {
    "start": 1004.733,
    "end": 1007.9,
    "text": "hỗ trợ thận nhẹ nhàng nước bột ấm giúp cơ thể thư giãn",
    "textdich": ""
  },
  {
    "start": 1008.366,
    "end": 1011.366,
    "text": "giảm áp lực Cho bàng quang từ đó hạn chế tiểu đêm",
    "textdich": ""
  },
  {
    "start": 1012.033,
    "end": 1014.4,
    "text": "4 ngủ sâu hơn khi uống vào buổi tối",
    "textdich": ""
  },
  {
    "start": 1014.833,
    "end": 1017.0,
    "text": "tính mát và dịu thần kinh của bột sắn dây",
    "textdich": ""
  },
  {
    "start": 1017.166,
    "end": 1018.733,
    "text": "giúp cô chú dễ dàng bước vào giấc ngủ",
    "textdich": ""
  },
  {
    "start": 1019.766,
    "end": 1020.566,
    "text": "giúp thanh lọc",
    "textdich": ""
  },
  {
    "start": 1020.733,
    "end": 1024.5,
    "text": "giải nhiệt nhờ có hoạt chất puerarin và isoflavon",
    "textdich": ""
  },
  {
    "start": 1024.9,
    "end": 1026.8,
    "text": "cơ thể được làm mát giải độc nhẹ",
    "textdich": ""
  },
  {
    "start": 1027.166,
    "end": 1028.633,
    "text": "thận không phải làm việc quá sức",
    "textdich": ""
  },
  {
    "start": 1029.533,
    "end": 1030.833,
    "text": "một số lưu ý quan trọng",
    "textdich": ""
  },
  {
    "start": 1031.733,
    "end": 1032.733,
    "text": "không uống quá nhiều",
    "textdich": ""
  },
  {
    "start": 1033.3,
    "end": 1034.566,
    "text": "mỗi ngày chỉ nên dùng một cốc",
    "textdich": ""
  },
  {
    "start": 1034.9,
    "end": 1035.933,
    "text": "tương đương một muỗng bột",
    "textdich": ""
  },
  {
    "start": 1036.433,
    "end": 1038.166,
    "text": "uống nhiều quá có thể gây lạnh bụng",
    "textdich": ""
  },
  {
    "start": 1038.3,
    "end": 1039.366,
    "text": "hoặc rối loạn tiêu hóa",
    "textdich": ""
  },
  {
    "start": 1040.033,
    "end": 1041.633,
    "text": "4 không Cho quá nhiều chanh",
    "textdich": ""
  },
  {
    "start": 1042.0,
    "end": 1044.6,
    "text": "chỉ nên nhỏ vài giọt vì chanh có tính axit",
    "textdich": ""
  },
  {
    "start": 1045.133,
    "end": 1048.4,
    "text": "nếu Cho nhiều bột dễ bị vón cục và làm hại dạ dày",
    "textdich": ""
  },
  {
    "start": 1049.366,
    "end": 1051.133,
    "text": "không dùng nước nguội phải dùng nước",
    "textdich": ""
  },
  {
    "start": 1051.133,
    "end": 1052.733,
    "text": "sôi nóng để bột chín hoàn toàn",
    "textdich": ""
  },
  {
    "start": 1053.333,
    "end": 1055.833,
    "text": "vừa an toàn vừa phát huy tác dụng tốt nhất",
    "textdich": ""
  },
  {
    "start": 1056.533,
    "end": 1058.933,
    "text": "4 người bị hạ huyết áp nặng cần tham khảo",
    "textdich": ""
  },
  {
    "start": 1059.1,
    "end": 1060.366,
    "text": "ý kiến bác sĩ trước khi dùng",
    "textdich": ""
  },
  {
    "start": 1060.766,
    "end": 1063.166,
    "text": "vì bột sắn dây có thể làm huyết áp hạ thêm",
    "textdich": ""
  },
  {
    "start": 1064.166,
    "end": 1065.5,
    "text": "chọn bột sắn dây nguyên chất",
    "textdich": ""
  },
  {
    "start": 1065.766,
    "end": 1067.3,
    "text": "cô chú nên mua ở nơi uy tín",
    "textdich": ""
  },
  {
    "start": 1067.733,
    "end": 1070.533,
    "text": "tránh mua loại có pha tạp bột khác vừa mất tác dụng",
    "textdich": ""
  },
  {
    "start": 1071.1,
    "end": 1072.333,
    "text": "vừa có thể gây hại Cho thận",
    "textdich": ""
  },
  {
    "start": 1072.933,
    "end": 1074.133,
    "text": "đây là kinh nghiệm thực tế",
    "textdich": ""
  },
  {
    "start": 1075.033,
    "end": 1077.2,
    "text": "tôi đã từng hướng dẫn nhiều cô chú thận yếu",
    "textdich": ""
  },
  {
    "start": 1077.3,
    "end": 1078.1,
    "text": "sử dụng bột sắn",
    "textdich": ""
  },
  {
    "start": 1078.133,
    "end": 1079.533,
    "text": "dây Theo cách pha chín này",
    "textdich": ""
  },
  {
    "start": 1080.033,
    "end": 1082.533,
    "text": "sau khoảng 2 đến BA tuần đa số đều nhận thấy",
    "textdich": ""
  },
  {
    "start": 1083.7,
    "end": 1085.433,
    "text": "số lần đi tiểu đêm giảm rõ rệt",
    "textdich": ""
  },
  {
    "start": 1086.333,
    "end": 1088.1,
    "text": "giấc ngủ sâu và ít mơ hơn",
    "textdich": ""
  },
  {
    "start": 1088.966,
    "end": 1092.2,
    "text": "cơ thể bớt nóng trong tinh thần nhẹ nhõm dễ chịu",
    "textdich": ""
  },
  {
    "start": 1092.9,
    "end": 1096.0,
    "text": "có một bác ngoài 65 tuổi từng tâm sự với tôi rằng",
    "textdich": ""
  },
  {
    "start": 1096.333,
    "end": 1099.033,
    "text": "trước đây mỗi đêm tôi dậy đi vệ sinh 4 đến năm lần",
    "textdich": ""
  },
  {
    "start": 1099.333,
    "end": 1100.233,
    "text": "ngủ chẳng được mấy",
    "textdich": ""
  },
  {
    "start": 1100.9,
    "end": 1103.4,
    "text": "nhưng sau khi uống bột sắn dây pha chín đều đặn",
    "textdich": ""
  },
  {
    "start": 1103.633,
    "end": 1104.9,
    "text": "giờ chỉ còn một đến 2 lần",
    "textdich": ""
  },
  {
    "start": 1105.2,
    "end": 1106.833,
    "text": "có hôm ngủ liền mạch đến sáng",
    "textdich": ""
  },
  {
    "start": 1107.366,
    "end": 1110.0,
    "text": "người khỏe hơn mà tâm trạng cũng vui vẻ hơn nhiều",
    "textdich": ""
  },
  {
    "start": 1111.033,
    "end": 1111.966,
    "text": "cô chú thân mến",
    "textdich": ""
  },
  {
    "start": 1112.233,
    "end": 1112.733,
    "text": "có thể nói",
    "textdich": ""
  },
  {
    "start": 1112.733,
    "end": 1114.966,
    "text": "cách pha chín bột sắn dây là phương pháp đơn giản",
    "textdich": ""
  },
  {
    "start": 1115.3,
    "end": 1117.9,
    "text": "nhưng an toàn và hiệu quả nhất để hỗ trợ thận yếu",
    "textdich": ""
  },
  {
    "start": 1118.433,
    "end": 1119.366,
    "text": "chỉ cần một muỗng bột",
    "textdich": ""
  },
  {
    "start": 1119.7,
    "end": 1121.433,
    "text": "một cốc nước sôi và một chút kiên trì",
    "textdich": ""
  },
  {
    "start": 1121.933,
    "end": 1123.766,
    "text": "cô chú đã có thêm một giải pháp dân gian",
    "textdich": ""
  },
  {
    "start": 1123.966,
    "end": 1124.833,
    "text": "giúp cải thiện sức khỏe",
    "textdich": ""
  },
  {
    "start": 1125.333,
    "end": 1127.433,
    "text": "giảm tiểu đêm và ngủ ngon hơn mỗi ngày",
    "textdich": ""
  },
  {
    "start": 1128.066,
    "end": 1128.733,
    "text": "bây giờ ở phần trước",
    "textdich": ""
  },
  {
    "start": 1129.0,
    "end": 1131.8,
    "text": "tôi đã hướng dẫn cô chú cách dùng bột sắn dây pha chín",
    "textdich": ""
  },
  {
    "start": 1132.166,
    "end": 1133.033,
    "text": "một phương pháp an toàn",
    "textdich": ""
  },
  {
    "start": 1133.733,
    "end": 1136.3,
    "text": "đơn giản và phù hợp Cho những AI có dạ dày nhạy cảm",
    "textdich": ""
  },
  {
    "start": 1136.5,
    "end": 1138.133,
    "text": "hoặc muốn cải thiện giấc ngủ buổi tối",
    "textdich": ""
  },
  {
    "start": 1138.9,
    "end": 1141.5,
    "text": "bây giờ tôi Xin chia sẻ cùng cô chú cách 2",
    "textdich": ""
  },
  {
    "start": 1141.7,
    "end": 1143.166,
    "text": "dùng sắn dây dưới dạng trà",
    "textdich": ""
  },
  {
    "start": 1143.633,
    "end": 1144.3,
    "text": "đây là cách uống",
    "textdich": ""
  },
  {
    "start": 1144.3,
    "end": 1146.3,
    "text": "rất thích hợp Cho những người muốn thanh lọc cơ thể",
    "textdich": ""
  },
  {
    "start": 1146.8,
    "end": 1147.7,
    "text": "giải độc nhẹ nhàng",
    "textdich": ""
  },
  {
    "start": 1147.8,
    "end": 1149.6,
    "text": "và hỗ trợ thận làm việc hiệu quả hơn",
    "textdich": ""
  },
  {
    "start": 1150.4,
    "end": 1152.533,
    "text": "Ba Vì SAO nên chọn uống trà sắn dây",
    "textdich": ""
  },
  {
    "start": 1153.333,
    "end": 1154.566,
    "text": "trong y học cổ truyền",
    "textdich": ""
  },
  {
    "start": 1154.966,
    "end": 1156.966,
    "text": "sắn dây hay còn gọi là cát căn",
    "textdich": ""
  },
  {
    "start": 1157.233,
    "end": 1158.533,
    "text": "vốn nổi tiếng với tính mát",
    "textdich": ""
  },
  {
    "start": 1158.833,
    "end": 1162.2,
    "text": "vị ngọt nhẹ và công dụng thanh nhiệt giải độc lợi tiểu",
    "textdich": ""
  },
  {
    "start": 1162.833,
    "end": 1164.9,
    "text": "người xưa thường dùng củ sắn dây phơi khô",
    "textdich": ""
  },
  {
    "start": 1165.233,
    "end": 1166.1,
    "text": "cắt lát mỏng",
    "textdich": ""
  },
  {
    "start": 1166.366,
    "end": 1169.3,
    "text": "đem sắc hoặc hãm như trà để uống thay nước trong ngày",
    "textdich": ""
  },
  {
    "start": 1169.933,
    "end": 1171.833,
    "text": "BA khác với cách pha bột sắn dây",
    "textdich": ""
  },
  {
    "start": 1172.133,
    "end": 1172.933,
    "text": "uống trà từ củ",
    "textdich": ""
  },
  {
    "start": 1173.1,
    "end": 1175.166,
    "text": "khô mang đến Cho cô chú cảm giác nhẹ nhàng",
    "textdich": ""
  },
  {
    "start": 1175.566,
    "end": 1176.366,
    "text": "thanh mát hơn",
    "textdich": ""
  },
  {
    "start": 1176.8,
    "end": 1178.8,
    "text": "đặc biệt người Cao tuổi bị nóng trong",
    "textdich": ""
  },
  {
    "start": 1179.133,
    "end": 1181.2,
    "text": "thường xuyên khát nước hay bốc hỏa",
    "textdich": ""
  },
  {
    "start": 1181.533,
    "end": 1182.733,
    "text": "hoặc có dấu hiệu tiểu đêm",
    "textdich": ""
  },
  {
    "start": 1183.166,
    "end": 1185.6,
    "text": "thì trà sắn dây chính là lựa chọn rất phù hợp",
    "textdich": ""
  },
  {
    "start": 1186.533,
    "end": 1188.5,
    "text": "cách làm trà sắn dây tại nhà BA",
    "textdich": ""
  },
  {
    "start": 1189.0,
    "end": 1190.733,
    "text": "để có một ấm trà sắn dây chuẩn",
    "textdich": ""
  },
  {
    "start": 1190.733,
    "end": 1192.966,
    "text": "vị cô chú có thể làm Theo các bước sau",
    "textdich": ""
  },
  {
    "start": 1193.966,
    "end": 1194.8,
    "text": "chuẩn bị nguyên liệu",
    "textdich": ""
  },
  {
    "start": 1195.566,
    "end": 1198.366,
    "text": "23 10g củ sắn dây khô đã thái lát mỏng",
    "textdich": ""
  },
  {
    "start": 1198.433,
    "end": 1199.4,
    "text": "nên chọn loại củ già",
    "textdich": ""
  },
  {
    "start": 1199.733,
    "end": 1202.833,
    "text": "bột nhiều khi khô thì có màu trắng ngà thơm dịu",
    "textdich": ""
  },
  {
    "start": 1203.766,
    "end": 1206.3,
    "text": "500 mi li lít 700 mi li lít nước sôi",
    "textdich": ""
  },
  {
    "start": 1207.3,
    "end": 1210.433,
    "text": "bình giữ nhiệt hoặc ấm hãm trà bằng gốm thủy tinh",
    "textdich": ""
  },
  {
    "start": 1210.933,
    "end": 1213.733,
    "text": "cách hãm Cho củ sắn dây đã thái lát vào bình",
    "textdich": ""
  },
  {
    "start": 1214.566,
    "end": 1215.8,
    "text": "rót nước sôi già vào",
    "textdich": ""
  },
  {
    "start": 1216.1,
    "end": 1218.333,
    "text": "đậy kín nắp hãm trong khoảng 20 phút",
    "textdich": ""
  },
  {
    "start": 1219.366,
    "end": 1220.1,
    "text": "sau đó",
    "textdich": ""
  },
  {
    "start": 1220.1,
    "end": 1222.4,
    "text": "cô chú sẽ có một ấm nước màu trắng trong hơi ngả",
    "textdich": ""
  },
  {
    "start": 1222.533,
    "end": 1225.333,
    "text": "vàng nhạt mùi thơm dịu mát đặc trưng của sắn dây",
    "textdich": ""
  },
  {
    "start": 1225.8,
    "end": 1228.533,
    "text": "cách uống có thể uống thay nước lọc trong ngày",
    "textdich": ""
  },
  {
    "start": 1228.966,
    "end": 1229.9,
    "text": "mỗi lần một cốc nhỏ",
    "textdich": ""
  },
  {
    "start": 1230.566,
    "end": 1232.233,
    "text": "4 uống khi còn ấm là tốt nhất",
    "textdich": ""
  },
  {
    "start": 1232.5,
    "end": 1235.4,
    "text": "vì nước ấm giúp cơ thể dễ hấp thụ và hỗ trợ tiêu hóa",
    "textdich": ""
  },
  {
    "start": 1236.433,
    "end": 1237.333,
    "text": "nếu thích uống mát",
    "textdich": ""
  },
  {
    "start": 1237.6,
    "end": 1240.2,
    "text": "cô chú có thể để nguội rồi Cho vào ngăn mát tủ lạnh",
    "textdich": ""
  },
  {
    "start": 1240.566,
    "end": 1241.366,
    "text": "dùng trong ngày",
    "textdich": ""
  },
  {
    "start": 1241.733,
    "end": 1242.4,
    "text": "tuy nhiên",
    "textdich": ""
  },
  {
    "start": 1242.4,
    "end": 1244.8,
    "text": "tôi khuyên cô chú hạn chế uống lạnh vào buổi tối",
    "textdich": ""
  },
  {
    "start": 1245.3,
    "end": 1246.766,
    "text": "để tránh gây kích thích bàng quang",
    "textdich": ""
  },
  {
    "start": 1247.366,
    "end": 1249.9,
    "text": "BA lợi ích của trà sắn dây với người thận yếu",
    "textdich": ""
  },
  {
    "start": 1250.766,
    "end": 1252.433,
    "text": "thanh nhiệt giải độc nhẹ nhàng",
    "textdich": ""
  },
  {
    "start": 1253.366,
    "end": 1255.133,
    "text": "trà sắn dây giúp làm mát cơ thể",
    "textdich": ""
  },
  {
    "start": 1255.5,
    "end": 1258.166,
    "text": "hỗ trợ gan và thận trong quá trình đào thải độc tố",
    "textdich": ""
  },
  {
    "start": 1259.2,
    "end": 1260.0,
    "text": "với người thận yếu",
    "textdich": ""
  },
  {
    "start": 1260.366,
    "end": 1261.5,
    "text": "việc giảm tải Cho thận",
    "textdich": ""
  },
  {
    "start": 1261.566,
    "end": 1263.0,
    "text": "bằng cách thanh lọc từ thực phẩm",
    "textdich": ""
  },
  {
    "start": 1263.133,
    "end": 1263.966,
    "text": "là vô cùng quan trọng",
    "textdich": ""
  },
  {
    "start": 1264.633,
    "end": 1266.133,
    "text": "BA giúp lợi tiểu tự nhiên",
    "textdich": ""
  },
  {
    "start": 1267.1,
    "end": 1268.5,
    "text": "nhờ tính mát và ngọt nhẹ",
    "textdich": ""
  },
  {
    "start": 1268.9,
    "end": 1271.366,
    "text": "trà sắn dây kích thích bàng quang làm việc cân bằng",
    "textdich": ""
  },
  {
    "start": 1271.833,
    "end": 1272.933,
    "text": "giúp tiểu tiện đều đặn",
    "textdich": ""
  },
  {
    "start": 1273.2,
    "end": 1275.8,
    "text": "không bí tiểu mà cũng không tiểu dồn dập BA",
    "textdich": ""
  },
  {
    "start": 1275.9,
    "end": 1276.7,
    "text": "điều này đặc biệt",
    "textdich": ""
  },
  {
    "start": 1276.766,
    "end": 1279.0,
    "text": "hữu ích Cho những cô chú hay bị tiểu đêm nhiều lần",
    "textdich": ""
  },
  {
    "start": 1279.366,
    "end": 1281.8,
    "text": "vì trà giúp điều chỉnh lại chức năng bài tiết",
    "textdich": ""
  },
  {
    "start": 1282.733,
    "end": 1283.533,
    "text": "hỗ trợ giấc ngủ",
    "textdich": ""
  },
  {
    "start": 1284.433,
    "end": 1286.966,
    "text": "khi cơ thể mát hơn độc tố được giải trừ",
    "textdich": ""
  },
  {
    "start": 1287.3,
    "end": 1288.733,
    "text": "thần kinh sẽ bớt căng thẳng",
    "textdich": ""
  },
  {
    "start": 1289.1,
    "end": 1290.9,
    "text": "dễ đưa cơ thể vào trạng thái thư giãn",
    "textdich": ""
  },
  {
    "start": 1291.833,
    "end": 1294.933,
    "text": "từ đó các cô chú có thể ngủ ngon ngủ sâu giấc hơn",
    "textdich": ""
  },
  {
    "start": 1295.833,
    "end": 1297.133,
    "text": "bổ sung khoáng chất tự nhiên",
    "textdich": ""
  },
  {
    "start": 1297.933,
    "end": 1301.0,
    "text": "trong củ sắn dây chứa một số hợp chất isoflavon",
    "textdich": ""
  },
  {
    "start": 1301.333,
    "end": 1304.5,
    "text": "puerarin có khả năng hỗ trợ tuần hoàn máu giảm mệt mỏi",
    "textdich": ""
  },
  {
    "start": 1304.9,
    "end": 1306.166,
    "text": "tăng cường sức khỏe Tim mạch",
    "textdich": ""
  },
  {
    "start": 1306.966,
    "end": 1308.966,
    "text": "đây là lợi ích gián tiếp nhưng rất quý",
    "textdich": ""
  },
  {
    "start": 1309.366,
    "end": 1310.5,
    "text": "bởi khi Tim mạch khỏe",
    "textdich": ""
  },
  {
    "start": 1310.9,
    "end": 1312.0,
    "text": "thận cũng bớt áp lực",
    "textdich": ""
  },
  {
    "start": 1312.933,
    "end": 1314.966,
    "text": "một số lưu ý khi uống trà sắn dây",
    "textdich": ""
  },
  {
    "start": 1315.566,
    "end": 1317.1,
    "text": "4 không dùng quá đậm đặc",
    "textdich": ""
  },
  {
    "start": 1317.366,
    "end": 1319.433,
    "text": "chỉ 23 10g củ sắn dây khô",
    "textdich": ""
  },
  {
    "start": 1319.533,
    "end": 1321.733,
    "text": "Cho 500 đến 700 mi li lít nước là đủ",
    "textdich": ""
  },
  {
    "start": 1322.4,
    "end": 1324.4,
    "text": "dùng quá nhiều có thể khiến cơ thể bị lạnh",
    "textdich": ""
  },
  {
    "start": 1324.433,
    "end": 1325.9,
    "text": "bụng đi ngoài phân lỏng",
    "textdich": ""
  },
  {
    "start": 1326.766,
    "end": 1327.633,
    "text": "không để qua đêm",
    "textdich": ""
  },
  {
    "start": 1327.966,
    "end": 1330.566,
    "text": "trà sắn dây để lâu sẽ dễ bị thiu biến chất",
    "textdich": ""
  },
  {
    "start": 1331.033,
    "end": 1333.0,
    "text": "cô chú nên uống hết trong ngày 4",
    "textdich": ""
  },
  {
    "start": 1333.333,
    "end": 1334.3,
    "text": "người huyết áp thấp",
    "textdich": ""
  },
  {
    "start": 1334.566,
    "end": 1336.233,
    "text": "cơ thể hàn lạnh cần cân nhắc",
    "textdich": ""
  },
  {
    "start": 1336.566,
    "end": 1337.733,
    "text": "vì trà có tính mát",
    "textdich": ""
  },
  {
    "start": 1338.0,
    "end": 1340.4,
    "text": "có thể làm người vốn đã lạnh càng dễ mệt mỏi hơn",
    "textdich": ""
  },
  {
    "start": 1341.533,
    "end": 1343.0,
    "text": "chọn củ sắn dây chất lượng",
    "textdich": ""
  },
  {
    "start": 1343.333,
    "end": 1347.1,
    "text": "khi mua nên chọn loại lát to màu trắng ngà thơm nhẹ",
    "textdich": ""
  },
  {
    "start": 1347.533,
    "end": 1349.433,
    "text": "không ẩm mốc không bị pha tạp",
    "textdich": ""
  },
  {
    "start": 1350.3,
    "end": 1352.033,
    "text": "tôi nhớ có một bác ngoài 70 tuổi",
    "textdich": ""
  },
  {
    "start": 1352.4,
    "end": 1353.766,
    "text": "vốn bị tiểu đêm nhiều năm",
    "textdich": ""
  },
  {
    "start": 1354.166,
    "end": 1357.166,
    "text": "lại hay cảm thấy cơ thể bốc hòa nóng bức vào buổi tối",
    "textdich": ""
  },
  {
    "start": 1357.766,
    "end": 1359.966,
    "text": "sau khi tôi hướng dẫn bác dùng trà sắn dây",
    "textdich": ""
  },
  {
    "start": 1360.133,
    "end": 1361.0,
    "text": "đều đặn mỗi ngày",
    "textdich": ""
  },
  {
    "start": 1361.433,
    "end": 1362.433,
    "text": "chỉ sau khoảng 2 tuần",
    "textdich": ""
  },
  {
    "start": 1362.766,
    "end": 1365.433,
    "text": "bác đã thấy rõ rệt số lần tiểu đêm giảm",
    "textdich": ""
  },
  {
    "start": 1365.8,
    "end": 1366.6,
    "text": "người mát mẻ",
    "textdich": ""
  },
  {
    "start": 1366.933,
    "end": 1370.033,
    "text": "dễ ngủ và đặc biệt là bụng dạ cũng nhẹ nhõm hơn",
    "textdich": ""
  },
  {
    "start": 1370.566,
    "end": 1371.6,
    "text": "bác còn vui vẻ bảo",
    "textdich": ""
  },
  {
    "start": 1371.833,
    "end": 1374.7,
    "text": "từ ngày uống trà sắn dây tôi thấy người như nhẹ Ra",
    "textdich": ""
  },
  {
    "start": 1375.0,
    "end": 1377.433,
    "text": "bụng ít đầy mà tinh thần cũng sảng khoái",
    "textdich": ""
  },
  {
    "start": 1378.366,
    "end": 1379.833,
    "text": "những trường hợp như vậy không hiếm",
    "textdich": ""
  },
  {
    "start": 1380.366,
    "end": 1382.233,
    "text": "và đây chính là Minh chứng Cho thấy trà",
    "textdich": ""
  },
  {
    "start": 1382.4,
    "end": 1383.0,
    "text": "sắn dây",
    "textdich": ""
  },
  {
    "start": 1383.0,
    "end": 1384.933,
    "text": "thực sự là người bạn đồng hành tốt với thận",
    "textdich": ""
  },
  {
    "start": 1385.0,
    "end": 1385.933,
    "text": "và sức khỏe toàn thân",
    "textdich": ""
  },
  {
    "start": 1386.766,
    "end": 1387.833,
    "text": "chào cô chú thân mến",
    "textdich": ""
  },
  {
    "start": 1388.1,
    "end": 1390.366,
    "text": "trà sắn dây là một phương pháp dân gian đơn giản",
    "textdich": ""
  },
  {
    "start": 1390.833,
    "end": 1393.233,
    "text": "rẻ tiền nhưng lại mang đến hiệu quả rất đáng quý",
    "textdich": ""
  },
  {
    "start": 1393.9,
    "end": 1396.9,
    "text": "chỉ cần vài lát củ sắn dây khô một bình nước sôi",
    "textdich": ""
  },
  {
    "start": 1397.2,
    "end": 1399.2,
    "text": "cô chú đã có Cho mình một thức uống thanh mát",
    "textdich": ""
  },
  {
    "start": 1399.533,
    "end": 1402.9,
    "text": "hỗ trợ thận giúp giảm tiểu đêm và cải thiện giấc ngủ",
    "textdich": ""
  },
  {
    "start": 1403.9,
    "end": 1405.833,
    "text": "tôi mong rằng qua chia sẻ này",
    "textdich": ""
  },
  {
    "start": 1406.133,
    "end": 1407.0,
    "text": "cô chú sẽ thử",
    "textdich": ""
  },
  {
    "start": 1407.1,
    "end": 1407.533,
    "text": "áp dụng",
    "textdich": ""
  },
  {
    "start": 1407.533,
    "end": 1409.933,
    "text": "và cảm nhận sự thay đổi tích cực trên cơ thể mình",
    "textdich": ""
  },
  {
    "start": 1410.533,
    "end": 1411.333,
    "text": "chỉ cần kiên trì",
    "textdich": ""
  },
  {
    "start": 1411.766,
    "end": 1413.533,
    "text": "kết hợp cùng chế độ ăn uống lành mạnh",
    "textdich": ""
  },
  {
    "start": 1413.733,
    "end": 1415.133,
    "text": "thì việc chặn đứng suy thận",
    "textdich": ""
  },
  {
    "start": 1415.366,
    "end": 1418.233,
    "text": "ngủ ngon hết tiểu đêm không còn là điều xa vời nữa",
    "textdich": ""
  },
  {
    "start": 1418.666,
    "end": 1421.933,
    "text": "4/4 lưu ý quan trọng khi người thận yếu dùng",
    "textdich": ""
  },
  {
    "start": 1422.8,
    "end": 1423.733,
    "text": "cô chú thân mến",
    "textdich": ""
  },
  {
    "start": 1424.3,
    "end": 1425.2,
    "text": "trong góc phần trước",
    "textdich": ""
  },
  {
    "start": 1425.4,
    "end": 1428.2,
    "text": "tôi đã chia sẻ với cô chú về công dụng của bột sắn dây",
    "textdich": ""
  },
  {
    "start": 1428.6,
    "end": 1430.1,
    "text": "cũng như 2 cách sử dụng phổ biến",
    "textdich": ""
  },
  {
    "start": 1430.433,
    "end": 1432.4,
    "text": "phá chín và hãm trà từ củ khô",
    "textdich": ""
  },
  {
    "start": 1432.966,
    "end": 1435.3,
    "text": "nhưng để bột sắn dây thật sự phát huy được hiệu quả",
    "textdich": ""
  },
  {
    "start": 1435.8,
    "end": 1437.333,
    "text": "đồng thời không gây tác dụng ngược",
    "textdich": ""
  },
  {
    "start": 1437.633,
    "end": 1439.033,
    "text": "thì có một điều vô cùng quan trọng",
    "textdich": ""
  },
  {
    "start": 1439.433,
    "end": 1441.733,
    "text": "cô chú cần phải nắm rõ những lưu ý khi sử dụng",
    "textdich": ""
  },
  {
    "start": 1442.3,
    "end": 1444.533,
    "text": "nhiều người vì quá tin vào công dụng mát gan",
    "textdich": ""
  },
  {
    "start": 1444.833,
    "end": 1446.733,
    "text": "giải độc của sắn dây mà uống quá liều",
    "textdich": ""
  },
  {
    "start": 1447.133,
    "end": 1449.533,
    "text": "uống Sai cách hoặc mua phải loại kém chất lượng",
    "textdich": ""
  },
  {
    "start": 1450.033,
    "end": 1451.333,
    "text": "dẫn đến rối loạn tiêu hóa",
    "textdich": ""
  },
  {
    "start": 1451.8,
    "end": 1454.833,
    "text": "hạ huyết áp thậm chí làm sức khỏe suy yếu thêm",
    "textdich": ""
  },
  {
    "start": 1455.833,
    "end": 1456.566,
    "text": "hôm nay",
    "textdich": ""
  },
  {
    "start": 1456.566,
    "end": 1458.833,
    "text": "tôi muốn cùng cô chú đi sâu vào những nguyên tắc",
    "textdich": ""
  },
  {
    "start": 1458.933,
    "end": 1460.533,
    "text": "an toàn khi dùng bột sắn dây",
    "textdich": ""
  },
  {
    "start": 1460.966,
    "end": 1462.1,
    "text": "để cô chú có thể yên tâm",
    "textdich": ""
  },
  {
    "start": 1462.2,
    "end": 1463.0,
    "text": "áp dụng hàng ngày",
    "textdich": ""
  },
  {
    "start": 1463.033,
    "end": 1465.133,
    "text": "mà vẫn bảo vệ được thận và giấc ngủ của mình",
    "textdich": ""
  },
  {
    "start": 1465.833,
    "end": 1469.0,
    "text": "6 một liều lượng chỉ nên một ly trên ngày",
    "textdich": ""
  },
  {
    "start": 1469.3,
    "end": 1470.366,
    "text": "tuyệt đối không lạm dụng",
    "textdich": ""
  },
  {
    "start": 1471.166,
    "end": 1473.833,
    "text": "bột sắn dây có tính mát giúp giải nhiệt rất tốt",
    "textdich": ""
  },
  {
    "start": 1474.333,
    "end": 1475.966,
    "text": "nhưng nếu uống nhiều sẽ gây lạnh bụng",
    "textdich": ""
  },
  {
    "start": 1476.2,
    "end": 1477.166,
    "text": "đi ngoài phân lỏng",
    "textdich": ""
  },
  {
    "start": 1477.566,
    "end": 1479.533,
    "text": "hoặc khiến cơ thể mất cân bằng âm dương",
    "textdich": ""
  },
  {
    "start": 1480.1,
    "end": 1481.366,
    "text": "BA với người thận yếu",
    "textdich": ""
  },
  {
    "start": 1481.733,
    "end": 1482.566,
    "text": "việc uống quá nhiều",
    "textdich": ""
  },
  {
    "start": 1482.7,
    "end": 1484.233,
    "text": "còn khiến thận phải làm việc liên tục",
    "textdich": ""
  },
  {
    "start": 1484.366,
    "end": 1486.1,
    "text": "để lọc và đào thải phần dư thừa",
    "textdich": ""
  },
  {
    "start": 1486.7,
    "end": 1489.366,
    "text": "vô tình tạo thêm áp lực Cho cơ quan vốn đã suy giảm",
    "textdich": ""
  },
  {
    "start": 1489.933,
    "end": 1492.633,
    "text": "nhưng tôi luôn khuyên cô chú chỉ nên uống một ly ngày",
    "textdich": ""
  },
  {
    "start": 1492.933,
    "end": 1495.233,
    "text": "tương đương khoảng 10 đến 15 giờ bột sắn dây",
    "textdich": ""
  },
  {
    "start": 1495.766,
    "end": 1496.733,
    "text": "đây là mức an toàn",
    "textdich": ""
  },
  {
    "start": 1497.233,
    "end": 1497.766,
    "text": "vừa đủ",
    "textdich": ""
  },
  {
    "start": 1497.766,
    "end": 1500.5,
    "text": "để cơ thể hấp thụ dưỡng chất mà không gây phản ứng phụ",
    "textdich": ""
  },
  {
    "start": 1501.1,
    "end": 1504.133,
    "text": "một 2 chọn bột sắn dây chuẩn nguyên chất",
    "textdich": ""
  },
  {
    "start": 1505.033,
    "end": 1506.0,
    "text": "trên thị trường hiện nay",
    "textdich": ""
  },
  {
    "start": 1506.433,
    "end": 1508.933,
    "text": "bột sắn dây bị làm giả hoặc pha tạp khá nhiều",
    "textdich": ""
  },
  {
    "start": 1509.366,
    "end": 1510.9,
    "text": "có loại bị trộn với bột mì",
    "textdich": ""
  },
  {
    "start": 1511.233,
    "end": 1514.3,
    "text": "bột sắn thường thậm chí là hóa chất để tạo mùi thơm",
    "textdich": ""
  },
  {
    "start": 1515.0,
    "end": 1516.433,
    "text": "nếu cô chú dùng phải loại này",
    "textdich": ""
  },
  {
    "start": 1516.8,
    "end": 1518.933,
    "text": "không những không có lợi mà còn gây hại Cho gan",
    "textdich": ""
  },
  {
    "start": 1519.2,
    "end": 1522.7,
    "text": "thận và gan 4 dấu hiệu bột chuẩn hạt bột trắng tinh",
    "textdich": ""
  },
  {
    "start": 1523.1,
    "end": 1526.5,
    "text": "đều khô tơi khi pha lên có mùi thơm nhẹ tự nhiên",
    "textdich": ""
  },
  {
    "start": 1526.9,
    "end": 1530.6,
    "text": "vị thanh mát không gắt năm dấu hiệu bột kém chất lượng",
    "textdich": ""
  },
  {
    "start": 1531.1,
    "end": 1534.133,
    "text": "màu xám vàng hoặc lẫn nhiều tạp chất mùi hắc",
    "textdich": ""
  },
  {
    "start": 1534.4,
    "end": 1537.033,
    "text": "dễ vón cục có mùi mốc hoặc mùi hóa chất",
    "textdich": ""
  },
  {
    "start": 1537.833,
    "end": 1540.6,
    "text": "BA khi mua cô chú nên chọn cơ sở uy tín",
    "textdich": ""
  },
  {
    "start": 1541.0,
    "end": 1542.0,
    "text": "có thương hiệu rõ ràng",
    "textdich": ""
  },
  {
    "start": 1542.366,
    "end": 1543.433,
    "text": "tránh mua hàng trôi nổi",
    "textdich": ""
  },
  {
    "start": 1544.433,
    "end": 1548.433,
    "text": "BA không uống sống đặc biệt là người già và trẻ em 4",
    "textdich": ""
  },
  {
    "start": 1548.766,
    "end": 1550.4,
    "text": "nhiều người có thói quen pha bột sắn",
    "textdich": ""
  },
  {
    "start": 1550.533,
    "end": 1551.9,
    "text": "dây với nước nguội để uống sống",
    "textdich": ""
  },
  {
    "start": 1552.233,
    "end": 1554.133,
    "text": "nghĩ rằng như vậy mới mát và giữ nguyên chất",
    "textdich": ""
  },
  {
    "start": 1554.7,
    "end": 1556.5,
    "text": "thực tế uống sống rất nguy hiểm",
    "textdich": ""
  },
  {
    "start": 1557.033,
    "end": 1559.766,
    "text": "nhất là với cô chú thận yếu hoặc có hệ tiêu hóa kém",
    "textdich": ""
  },
  {
    "start": 1560.6,
    "end": 1562.766,
    "text": "4 bột sống khi vào cơ thể sẽ khó tiêu hóa",
    "textdich": ""
  },
  {
    "start": 1563.2,
    "end": 1565.933,
    "text": "dễ gây đầy bụng tiêu chảy đau quặn bụng",
    "textdich": ""
  },
  {
    "start": 1566.833,
    "end": 1567.933,
    "text": "đặc biệt người già",
    "textdich": ""
  },
  {
    "start": 1568.433,
    "end": 1570.3,
    "text": "trẻ nhỏ và người đang có bệnh dạ dày",
    "textdich": ""
  },
  {
    "start": 1570.766,
    "end": 1572.433,
    "text": "đại tràng tuyệt đối không nên uống sống",
    "textdich": ""
  },
  {
    "start": 1573.133,
    "end": 1575.566,
    "text": "BA cách tốt nhất vẫn là pha chín với nước sôi",
    "textdich": ""
  },
  {
    "start": 1575.633,
    "end": 1576.433,
    "text": "để vừa an toàn",
    "textdich": ""
  },
  {
    "start": 1576.833,
    "end": 1577.7,
    "text": "vừa dễ hấp thu",
    "textdich": ""
  },
  {
    "start": 1578.766,
    "end": 1582.633,
    "text": "4 người huyết áp thấp cơ thể hàn lạnh nên thận trọng",
    "textdich": ""
  },
  {
    "start": 1583.433,
    "end": 1586.333,
    "text": "4 bột sắn dây có tính mát làm hạ nhiệt cơ thể",
    "textdich": ""
  },
  {
    "start": 1587.033,
    "end": 1589.2,
    "text": "với những cô chú vốn có thể trạng Hàn lạnh",
    "textdich": ""
  },
  {
    "start": 1589.5,
    "end": 1590.5,
    "text": "hay bị chân Tay lạnh",
    "textdich": ""
  },
  {
    "start": 1590.766,
    "end": 1592.4,
    "text": "ăn uống kém tiêu hóa yếu",
    "textdich": ""
  },
  {
    "start": 1592.8,
    "end": 1594.133,
    "text": "hoặc huyết áp vốn đã thấp",
    "textdich": ""
  },
  {
    "start": 1594.366,
    "end": 1595.8,
    "text": "thì nếu uống nhiều bột sắn dây",
    "textdich": ""
  },
  {
    "start": 1595.933,
    "end": 1597.7,
    "text": "sẽ càng làm tình trạng trầm trọng hơn",
    "textdich": ""
  },
  {
    "start": 1598.3,
    "end": 1601.7,
    "text": "4 biểu hiện dễ thấy là HOA mắt chóng mặt người mệt mỏi",
    "textdich": ""
  },
  {
    "start": 1602.033,
    "end": 1602.833,
    "text": "lạnh bụng",
    "textdich": ""
  },
  {
    "start": 1603.366,
    "end": 1604.166,
    "text": "trong trường hợp này",
    "textdich": ""
  },
  {
    "start": 1604.6,
    "end": 1607.166,
    "text": "nếu muốn dùng cô chú chỉ nên dùng lượng rất nhỏ",
    "textdich": ""
  },
  {
    "start": 1607.5,
    "end": 1610.3,
    "text": "uống loãng và tuyệt đối không uống vào buổi tối lạnh",
    "textdich": ""
  },
  {
    "start": 1611.233,
    "end": 1614.566,
    "text": "năm phụ nữ mang Thai yếu dễ tụt huyết áp",
    "textdich": ""
  },
  {
    "start": 1614.933,
    "end": 1616.1,
    "text": "cần hỏi ý kiến bác sĩ",
    "textdich": ""
  },
  {
    "start": 1616.8,
    "end": 1620.9,
    "text": "4 sắn dây có một số hoạt chất isoflavon và puerarin",
    "textdich": ""
  },
  {
    "start": 1621.233,
    "end": 1622.9,
    "text": "tác động đến nội tiết và mạch máu",
    "textdich": ""
  },
  {
    "start": 1623.566,
    "end": 1624.533,
    "text": "với phụ nữ mang Thai",
    "textdich": ""
  },
  {
    "start": 1625.0,
    "end": 1626.8,
    "text": "nhất là người có tiền sử tụt huyết áp",
    "textdich": ""
  },
  {
    "start": 1627.133,
    "end": 1629.6,
    "text": "cơ thể yếu việc uống bột sắn dây không đúng cách",
    "textdich": ""
  },
  {
    "start": 1629.633,
    "end": 1630.633,
    "text": "có thể gây choáng váng",
    "textdich": ""
  },
  {
    "start": 1631.033,
    "end": 1633.333,
    "text": "khó chịu thậm chí không tốt Cho Thai kỳ",
    "textdich": ""
  },
  {
    "start": 1634.233,
    "end": 1635.133,
    "text": "tôi luôn nhấn mạnh",
    "textdich": ""
  },
  {
    "start": 1635.4,
    "end": 1637.366,
    "text": "phụ nữ mang Thai cần hỏi ý kiến bác sĩ",
    "textdich": ""
  },
  {
    "start": 1637.533,
    "end": 1639.1,
    "text": "trước khi dùng bất kỳ loại thảo dược nào",
    "textdich": ""
  },
  {
    "start": 1639.6,
    "end": 1640.566,
    "text": "kể cả bột sắn dây",
    "textdich": ""
  },
  {
    "start": 1641.6,
    "end": 1644.3,
    "text": "6 không tự ý trộn với các thảo dược khác",
    "textdich": ""
  },
  {
    "start": 1645.166,
    "end": 1647.633,
    "text": "nhiều cô chú thường có thói quen càng nhiều càng tốt",
    "textdich": ""
  },
  {
    "start": 1647.966,
    "end": 1649.366,
    "text": "nên hay trộn bột sắn dây",
    "textdich": ""
  },
  {
    "start": 1649.5,
    "end": 1651.166,
    "text": "với các loại thảo dược khác để uống cùng",
    "textdich": ""
  },
  {
    "start": 1651.766,
    "end": 1654.566,
    "text": "nhưng điều này lại tiềm ẩn nguy cơ tương tác dược tính",
    "textdich": ""
  },
  {
    "start": 1654.966,
    "end": 1655.966,
    "text": "khiến hiệu quả giảm đi",
    "textdich": ""
  },
  {
    "start": 1656.433,
    "end": 1659.1,
    "text": "thậm chí gây phản tác dụng 4 ví dụ",
    "textdich": ""
  },
  {
    "start": 1659.5,
    "end": 1661.733,
    "text": "kết hợp với một số vị thuốc có tính Hàn khác",
    "textdich": ""
  },
  {
    "start": 1661.966,
    "end": 1663.433,
    "text": "có thể khiến cơ thể bị lạnh quá mức",
    "textdich": ""
  },
  {
    "start": 1663.766,
    "end": 1665.566,
    "text": "tiêu chảy mất cân bằng khí huyết",
    "textdich": ""
  },
  {
    "start": 1666.566,
    "end": 1668.7,
    "text": "do đó nếu cô chú muốn kết hợp",
    "textdich": ""
  },
  {
    "start": 1669.033,
    "end": 1670.633,
    "text": "hãy tham khảo ý kiến bác sĩ đông",
    "textdich": ""
  },
  {
    "start": 1670.766,
    "end": 1672.233,
    "text": "y hoặc thầy thuốc có kinh nghiệm",
    "textdich": ""
  },
  {
    "start": 1672.566,
    "end": 1673.766,
    "text": "đừng tự ý pha trộn",
    "textdich": ""
  },
  {
    "start": 1674.433,
    "end": 1677.0,
    "text": "6 7 thời điểm uống cũng rất quan trọng",
    "textdich": ""
  },
  {
    "start": 1677.9,
    "end": 1679.8,
    "text": "7 buổi tối trước khi ngủ một đến 2 tiếng",
    "textdich": ""
  },
  {
    "start": 1680.2,
    "end": 1682.733,
    "text": "thích hợp Cho người muốn giảm tiểu đêm ngủ ngon",
    "textdich": ""
  },
  {
    "start": 1683.133,
    "end": 1685.1,
    "text": "8 ban ngày khi trời nóng",
    "textdich": ""
  },
  {
    "start": 1685.433,
    "end": 1687.4,
    "text": "có thể uống trà sắn dây để giải nhiệt",
    "textdich": ""
  },
  {
    "start": 1688.1,
    "end": 1690.966,
    "text": "bác tránh uống lúc bụng đói vì dễ gây cồn cào",
    "textdich": ""
  },
  {
    "start": 1691.366,
    "end": 1692.366,
    "text": "khó chịu Cho dạ dày",
    "textdich": ""
  },
  {
    "start": 1693.3,
    "end": 1695.033,
    "text": "tôi từng gặp một bác 62 tuổi",
    "textdich": ""
  },
  {
    "start": 1695.4,
    "end": 1697.1,
    "text": "bị thận yếu và hay tiểu đêm",
    "textdich": ""
  },
  {
    "start": 1697.7,
    "end": 1699.5,
    "text": "lúc đầu bác nghe người quen mách",
    "textdich": ""
  },
  {
    "start": 1699.733,
    "end": 1702.033,
    "text": "mỗi ngày uống BA cốc bột sắn dây sống bác",
    "textdich": ""
  },
  {
    "start": 1702.2,
    "end": 1704.133,
    "text": "sau một tuần bác thấy bụng khó chịu",
    "textdich": ""
  },
  {
    "start": 1704.4,
    "end": 1705.333,
    "text": "tiêu chảy liên tục",
    "textdich": ""
  },
  {
    "start": 1705.6,
    "end": 1707.833,
    "text": "người mất sức thậm chí mệt mỏi hơn trước",
    "textdich": ""
  },
  {
    "start": 1708.533,
    "end": 1710.333,
    "text": "sau khi tôi giải thích và hướng dẫn lại",
    "textdich": ""
  },
  {
    "start": 1710.5,
    "end": 1711.5,
    "text": "chỉ uống một ly ngày",
    "textdich": ""
  },
  {
    "start": 1711.8,
    "end": 1713.6,
    "text": "pha chín dùng trước khi ngủ",
    "textdich": ""
  },
  {
    "start": 1713.966,
    "end": 1714.9,
    "text": "thì khoảng 2 tuần sau",
    "textdich": ""
  },
  {
    "start": 1715.4,
    "end": 1717.633,
    "text": "bác đã thấy cải thiện rõ rệt tiểu đêm giảm",
    "textdich": ""
  },
  {
    "start": 1718.033,
    "end": 1720.0,
    "text": "bụng dạ dễ chịu ngủ sâu hơn",
    "textdich": ""
  },
  {
    "start": 1720.7,
    "end": 1722.5,
    "text": "nhưng qua đó có thể thấy rằng",
    "textdich": ""
  },
  {
    "start": 1722.566,
    "end": 1724.2,
    "text": "uống đúng cách quan trọng hơn rất nhiều",
    "textdich": ""
  },
  {
    "start": 1724.3,
    "end": 1725.1,
    "text": "so với uống nhiều",
    "textdich": ""
  },
  {
    "start": 1725.933,
    "end": 1726.833,
    "text": "cô chú thân mến",
    "textdich": ""
  },
  {
    "start": 1727.033,
    "end": 1729.433,
    "text": "bột sắn dây là món quà dân gian quý giá",
    "textdich": ""
  },
  {
    "start": 1729.9,
    "end": 1731.4,
    "text": "vừa rẻ vừa dễ tìm",
    "textdich": ""
  },
  {
    "start": 1731.8,
    "end": 1734.0,
    "text": "lại mang nhiều công dụng tốt Cho thận và giấc ngủ",
    "textdich": ""
  },
  {
    "start": 1734.6,
    "end": 1737.433,
    "text": "nhưng nếu dùng Sai cách thì lợi bất cập hại",
    "textdich": ""
  },
  {
    "start": 1737.833,
    "end": 1739.566,
    "text": "tôi hi vọng rằng qua phần chia sẻ này",
    "textdich": ""
  },
  {
    "start": 1740.0,
    "end": 1742.0,
    "text": "cô chú đã nắm rõ những lưu ý cần thiết",
    "textdich": ""
  },
  {
    "start": 1742.4,
    "end": 1745.5,
    "text": "uống vừa đủ chọn bột chuẩn pha chín mới an toàn",
    "textdich": ""
  },
  {
    "start": 1745.8,
    "end": 1747.2,
    "text": "lưu ý thể trạng riêng của mình",
    "textdich": ""
  },
  {
    "start": 1747.9,
    "end": 1749.566,
    "text": "4 chỉ cần tuân thủ những điều này",
    "textdich": ""
  },
  {
    "start": 1749.766,
    "end": 1750.566,
    "text": "bột sắn dây",
    "textdich": ""
  },
  {
    "start": 1750.7,
    "end": 1753.133,
    "text": "sẽ thực sự trở thành người bạn đồng hành đáng tin cậy",
    "textdich": ""
  },
  {
    "start": 1753.5,
    "end": 1754.8,
    "text": "giúp cô chú bảo vệ thận",
    "textdich": ""
  },
  {
    "start": 1755.133,
    "end": 1758.1,
    "text": "giảm tiểu đêm và tìm lại giấc ngủ sâu trọn vẹn",
    "textdich": ""
  },
  {
    "start": 1758.6,
    "end": 1759.5,
    "text": "chào cô chú thân mến",
    "textdich": ""
  },
  {
    "start": 1760.166,
    "end": 1760.933,
    "text": "đến đây",
    "textdich": ""
  },
  {
    "start": 1760.933,
    "end": 1763.333,
    "text": "sau khi tôi và cô chú đã cùng nhau đi qua từng phần",
    "textdich": ""
  },
  {
    "start": 1763.533,
    "end": 1765.3,
    "text": "từ việc hiểu bột sắn dây là gì",
    "textdich": ""
  },
  {
    "start": 1765.5,
    "end": 1766.433,
    "text": "tại SAO tốt Cho thận",
    "textdich": ""
  },
  {
    "start": 1766.733,
    "end": 1768.8,
    "text": "đến những lợi ích rõ rệt như ngăn suy thận",
    "textdich": ""
  },
  {
    "start": 1769.033,
    "end": 1769.833,
    "text": "giảm tiểu đêm",
    "textdich": ""
  },
  {
    "start": 1770.166,
    "end": 1771.566,
    "text": "giúp ngủ sâu cũng như",
    "textdich": ""
  },
  {
    "start": 1771.566,
    "end": 1773.966,
    "text": "cách pha chế an toàn và những lưu ý cần nhớ",
    "textdich": ""
  },
  {
    "start": 1774.3,
    "end": 1776.0,
    "text": "chắc hẳn cô chú đã thấy rõ một điều",
    "textdich": ""
  },
  {
    "start": 1776.766,
    "end": 1778.766,
    "text": "đôi khi chính những nguyên liệu dân dã",
    "textdich": ""
  },
  {
    "start": 1779.166,
    "end": 1780.166,
    "text": "quen thuộc trong bếp Việt",
    "textdich": ""
  },
  {
    "start": 1780.3,
    "end": 1782.133,
    "text": "lại mang trong mình sức mạnh tuyệt vời để gìn",
    "textdich": ""
  },
  {
    "start": 1782.3,
    "end": 1783.1,
    "text": "giữ sức khỏe",
    "textdich": ""
  },
  {
    "start": 1783.8,
    "end": 1785.7,
    "text": "tôi muốn nhấn mạnh lại với cô chú rằng",
    "textdich": ""
  },
  {
    "start": 1786.166,
    "end": 1787.2,
    "text": "chỉ cần biết dùng đúng cách",
    "textdich": ""
  },
  {
    "start": 1787.5,
    "end": 1789.633,
    "text": "bột sắn dây thức quả quê bình dị",
    "textdich": ""
  },
  {
    "start": 1790.1,
    "end": 1791.733,
    "text": "hoàn toàn có thể trở thành một vị cứu",
    "textdich": ""
  },
  {
    "start": 1791.833,
    "end": 1793.133,
    "text": "tinh Cho những AI đang thận yếu",
    "textdich": ""
  },
  {
    "start": 1793.733,
    "end": 1795.833,
    "text": "nhiều người cứ nghĩ phải tìm đến thuốc đắt tiền",
    "textdich": ""
  },
  {
    "start": 1796.133,
    "end": 1797.566,
    "text": "thực phẩm chức năng xa xỉ",
    "textdich": ""
  },
  {
    "start": 1798.0,
    "end": 1798.8,
    "text": "nhưng thực Ra",
    "textdich": ""
  },
  {
    "start": 1799.0,
    "end": 1801.133,
    "text": "đôi khi chỉ cần một chén bột sắn dây ấm",
    "textdich": ""
  },
  {
    "start": 1801.433,
    "end": 1802.233,
    "text": "uống trước khi ngủ",
    "textdich": ""
  },
  {
    "start": 1802.533,
    "end": 1804.933,
    "text": "cơ thể đã dần được thanh lọc thận được giảm tải",
    "textdich": ""
  },
  {
    "start": 1805.5,
    "end": 1807.133,
    "text": "giấc ngủ cũng trở nên yên lành hơn",
    "textdich": ""
  },
  {
    "start": 1808.033,
    "end": 1810.1,
    "text": "tôi đã từng nghe nhiều cô chú chia sẻ rằng",
    "textdich": ""
  },
  {
    "start": 1810.433,
    "end": 1812.633,
    "text": "từ ngày uống bột sắn dây Theo cách con hướng dẫn",
    "textdich": ""
  },
  {
    "start": 1813.033,
    "end": 1813.966,
    "text": "đêm ngủ ngon hơn",
    "textdich": ""
  },
  {
    "start": 1814.4,
    "end": 1816.3,
    "text": "không còn phải chở dậy nhiều lần đi vệ sinh",
    "textdich": ""
  },
  {
    "start": 1817.033,
    "end": 1819.2,
    "text": "sáng Ra tỉnh táo dễ chịu hơn hẳn",
    "textdich": ""
  },
  {
    "start": 1819.733,
    "end": 1820.566,
    "text": "nghe những lời đó",
    "textdich": ""
  },
  {
    "start": 1820.833,
    "end": 1822.033,
    "text": "thật sự tôi cũng xúc động",
    "textdich": ""
  },
  {
    "start": 1822.333,
    "end": 1824.533,
    "text": "vì thấy rõ một bài thuốc dân gian giản dị",
    "textdich": ""
  },
  {
    "start": 1824.633,
    "end": 1826.733,
    "text": "mà lại có sức mạnh cải thiện đời sống thực sự",
    "textdich": ""
  },
  {
    "start": 1827.366,
    "end": 1829.966,
    "text": "và cô chú biết không khi cơ thể ngủ đủ giấc",
    "textdich": ""
  },
  {
    "start": 1830.233,
    "end": 1832.633,
    "text": "tâm trí thả lỏng thì thận cũng được bảo vệ",
    "textdich": ""
  },
  {
    "start": 1833.1,
    "end": 1833.533,
    "text": "nguy cơ",
    "textdich": ""
  },
  {
    "start": 1833.533,
    "end": 1835.733,
    "text": "tiến triển thành suy thận nặng dần được chặn lại",
    "textdich": ""
  },
  {
    "start": 1836.366,
    "end": 1837.833,
    "text": "nhưng tôi tin rằng bột sắn",
    "textdich": ""
  },
  {
    "start": 1838.0,
    "end": 1839.4,
    "text": "dây không chỉ là một loại thực phẩm",
    "textdich": ""
  },
  {
    "start": 1839.733,
    "end": 1841.766,
    "text": "mà còn là một người bạn đồng hành cùng cô chú",
    "textdich": ""
  },
  {
    "start": 1841.9,
    "end": 1843.766,
    "text": "trong hành trình bảo vệ sức khỏe tuổi già",
    "textdich": ""
  },
  {
    "start": 1844.533,
    "end": 1847.4,
    "text": "nhưng điều quan trọng nhất là dùng đúng liều",
    "textdich": ""
  },
  {
    "start": 1847.9,
    "end": 1849.133,
    "text": "chọn đúng loại bột nguyên chất",
    "textdich": ""
  },
  {
    "start": 1849.433,
    "end": 1850.6,
    "text": "và lắng nghe cơ thể mình",
    "textdich": ""
  },
  {
    "start": 1851.133,
    "end": 1853.533,
    "text": "đừng lạm dụng đừng tin vào những lời thổi phồng",
    "textdich": ""
  },
  {
    "start": 1854.0,
    "end": 1856.566,
    "text": "mà hãy để thiên nhiên hỗ trợ cơ thể một cách bền vững",
    "textdich": ""
  },
  {
    "start": 1856.9,
    "end": 1857.7,
    "text": "từ tốn",
    "textdich": ""
  },
  {
    "start": 1858.166,
    "end": 1859.4,
    "text": "hôm nay cô chú thử tưởng tượng",
    "textdich": ""
  },
  {
    "start": 1859.733,
    "end": 1862.0,
    "text": "mỗi tối thay vì lo lắng vì mất ngủ",
    "textdich": ""
  },
  {
    "start": 1862.4,
    "end": 1865.2,
    "text": "tiểu đêm thì nay chỉ cần một ly bột sắn dây ấm",
    "textdich": ""
  },
  {
    "start": 1865.533,
    "end": 1866.633,
    "text": "thơm nhẹ uống vào",
    "textdich": ""
  },
  {
    "start": 1867.0,
    "end": 1867.9,
    "text": "cơ thể được làm mát",
    "textdich": ""
  },
  {
    "start": 1868.233,
    "end": 1869.5,
    "text": "bàng quang bớt kích thích",
    "textdich": ""
  },
  {
    "start": 1869.833,
    "end": 1871.133,
    "text": "giấc ngủ kéo đến nhẹ nhàng",
    "textdich": ""
  },
  {
    "start": 1871.933,
    "end": 1873.733,
    "text": "sáng mai cô chú mở mắt Ra",
    "textdich": ""
  },
  {
    "start": 1874.033,
    "end": 1875.5,
    "text": "thấy mình đã ngủ yên một mạch",
    "textdich": ""
  },
  {
    "start": 1875.766,
    "end": 1876.566,
    "text": "không còn nặng đầu",
    "textdich": ""
  },
  {
    "start": 1876.933,
    "end": 1877.733,
    "text": "không còn mệt mỏi",
    "textdich": ""
  },
  {
    "start": 1878.2,
    "end": 1880.533,
    "text": "và đó chính là điều mà tôi mong cô chú đạt được",
    "textdich": ""
  },
  {
    "start": 1881.333,
    "end": 1883.9,
    "text": "và trước khi kết thúc tôi muốn nhắn nhủ rằng",
    "textdich": ""
  },
  {
    "start": 1884.233,
    "end": 1885.333,
    "text": "sức khỏe là hành trình",
    "textdich": ""
  },
  {
    "start": 1885.733,
    "end": 1886.7,
    "text": "không phải phép màu",
    "textdich": ""
  },
  {
    "start": 1887.3,
    "end": 1889.133,
    "text": "nhưng nếu mỗi ngày cô chú biết tận dụng",
    "textdich": ""
  },
  {
    "start": 1889.2,
    "end": 1890.2,
    "text": "những món quà tự nhiên",
    "textdich": ""
  },
  {
    "start": 1890.3,
    "end": 1891.9,
    "text": "quanh mình như bột sắn dây",
    "textdich": ""
  },
  {
    "start": 1892.133,
    "end": 1894.933,
    "text": "thì hành trình đó sẽ nhẹ nhàng và tràn đầy hi vọng hơn",
    "textdich": ""
  },
  {
    "start": 1895.8,
    "end": 1897.833,
    "text": "nếu cô chú thấy những chia sẻ này hữu ích",
    "textdich": ""
  },
  {
    "start": 1898.166,
    "end": 1899.133,
    "text": "Xin hãy ấn like",
    "textdich": ""
  },
  {
    "start": 1899.5,
    "end": 1900.633,
    "text": "để lại bình luận bên dưới",
    "textdich": ""
  },
  {
    "start": 1900.766,
    "end": 1902.3,
    "text": "để tôi biết cảm nhận của cô chú",
    "textdich": ""
  },
  {
    "start": 1902.833,
    "end": 1904.533,
    "text": "và đặc biệt là nhấn đăng ký kênh",
    "textdich": ""
  },
  {
    "start": 1905.0,
    "end": 1906.6,
    "text": "bởi vì mỗi video tôi làm",
    "textdich": ""
  },
  {
    "start": 1906.6,
    "end": 1909.233,
    "text": "đều mong muốn mang đến Cho cô chú một bí quyết dân gian",
    "textdich": ""
  },
  {
    "start": 1909.6,
    "end": 1912.633,
    "text": "một lời khuyên y khoa để chúng ta cùng nhau sống khỏe",
    "textdich": ""
  },
  {
    "start": 1913.033,
    "end": 1914.8,
    "text": "sống vui và sống lâu hơn",
    "textdich": ""
  },
  {
    "start": 1915.5,
    "end": 1917.133,
    "text": "vâng và nếu cô chú có bạn bè",
    "textdich": ""
  },
  {
    "start": 1917.433,
    "end": 1919.366,
    "text": "người thân cũng đang vật lộn với thận yếu",
    "textdich": ""
  },
  {
    "start": 1919.766,
    "end": 1922.966,
    "text": "mất ngủ tiểu đêm hãy chia sẻ VI đê ô này Cho họ",
    "textdich": ""
  },
  {
    "start": 1923.5,
    "end": 1926.2,
    "text": "biết đâu một ly bột sắn dây lại trở thành chìa khóa",
    "textdich": ""
  },
  {
    "start": 1926.333,
    "end": 1929.166,
    "text": "mở Ra giấc ngủ ngon và sức khỏe vững vàng Cho họ",
    "textdich": ""
  },
  {
    "start": 1930.1,
    "end": 1932.5,
    "text": "tôi tin khi chúng ta trao đi điều hữu ích",
    "textdich": ""
  },
  {
    "start": 1932.9,
    "end": 1934.8,
    "text": "niềm vui sẽ trở lại gấp bội phần thưởng",
    "textdich": ""
  }
]